Workbook

Sheet HH Deposit Balance Comparison
A1: Household ID | B1: Household Name | C1: Officer Code | D1: Officer Name | E1: % of Deposits to Loans (Current) | F1: % of Deposits to Loans (Prior) | G1: % of Deposits to Loans (YTD) | H1: Current Month-end Deposit Balance | I1: Prior Month-end Deposit Balance | J1: Prior Year-end Deposit Balance | K1: Deposit Balance Change Month-over-Month | L1: Deposit Balance Change Year-to-date
A2: 1 | B2: MODERN BOOKKEEPING HOUSEHOLD | C2: Mark Morrison | D2: 615 | E2: =_xlfn.XLOOKUP(A2,'Current Month'!A:A,'Current Month'!I:I,"") -> 24.431643 | F2: =_xlfn.XLOOKUP(A2,'Prior Month'!A:A,'Prior Month'!I:I,"") -> 25.568844 | G2: =_xlfn.XLOOKUP(A2,'Year end 2024'!A:A,'Year end 2024'!I:I,"") -> 20.153983 | H2: =_xlfn.XLOOKUP(A2,'Current Month'!A:A,'Current Month'!E:E,0,0) -> 33327940 | I2: =_xlfn.XLOOKUP(A2,'Prior Month'!A:A,'Prior Month'!E:E,0,0) -> 34935884 | J2: =_xlfn.XLOOKUP(A2,'Year end 2024'!A:A,'Year end 2024'!E:E,0,0) -> 37995705 | K2: =IFERROR(SUM(H2-I2),H2) -> -1607943.4 | L2: =IFERROR(SUM(H2-J2),H2) -> -4667764.3
A3: 10 | B3: MARK CHERRY HOUSEHOLD | C3: Brad Kirkland | D3: 618 | E3: =_xlfn.XLOOKUP(A3,'Current Month'!A:A,'Current Month'!I:I,"") -> 0.13707749 | F3: =_xlfn.XLOOKUP(A3,'Prior Month'!A:A,'Prior Month'!I:I,"") -> 0.10933623 | G3: =_xlfn.XLOOKUP(A3,'Year end 2024'!A:A,'Year end 2024'!I:I,"") -> 0.031256665 | H3: =_xlfn.XLOOKUP(A3,'Current Month'!A:A,'Current Month'!E:E,0,0) -> 165289.76 | I3: =_xlfn.XLOOKUP(A3,'Prior Month'!A:A,'Prior Month'!E:E,0,0) -> 132546.61 | J3: =_xlfn.XLOOKUP(A3,'Year end 2024'!A:A,'Year end 2024'!E:E,0,0) -> 23095.28 | K3: =IFERROR(SUM(H3-I3),H3) -> 32743.15 | L3: =IFERROR(SUM(H3-J3),H3) -> 142194.48
A4: 100 | B4: Glenn A Bianchini Household | C4: Julie Jones | D4: 251 | E4: =_xlfn.XLOOKUP(A4,'Current Month'!A:A,'Current Month'!I:I,"") | F4: =_xlfn.XLOOKUP(A4,'Prior Month'!A:A,'Prior Month'!I:I,"") | G4: =_xlfn.XLOOKUP(A4,'Year end 2024'!A:A,'Year end 2024'!I:I,"") | H4: =_xlfn.XLOOKUP(A4,'Current Month'!A:A,'Current Month'!E:E,0,0) -> 22867.55 | I4: =_xlfn.XLOOKUP(A4,'Prior Month'!A:A,'Prior Month'!E:E,0,0) -> 23748.96 | J4: =_xlfn.XLOOKUP(A4,'Year end 2024'!A:A,'Year end 2024'!E:E,0,0) -> 28115.12 | K4: =IFERROR(SUM(H4-I4),H4) -> -881.41 | L4: =IFERROR(SUM(H4-J4),H4) -> -5247.57
A5: 1000 | B5: FUEL CELL ESA WCSU LLC HOUSEHOLD | C5: Mark Matheson | D5: 675 | E5: =_xlfn.XLOOKUP(A5,'Current Month'!A:A,'Current Month'!I:I,"") | F5: =_xlfn.XLOOKUP(A5,'Prior Month'!A:A,'Prior Month'!I:I,"") | G5: =_xlfn.XLOOKUP(A5,'Year end 2024'!A:A,'Year end 2024'!I:I,"") | H5: =_xlfn.XLOOKUP(A5,'Current Month'!A:A,'Current Month'!E:E,0,0) -> 0 | I5: =_xlfn.XLOOKUP(A5,'Prior Month'!A:A,'Prior Month'!E:E,0,0) -> 0 | J5: =_xlfn.XLOOKUP(A5,'Year end 2024'!A:A,'Year end 2024'!E:E,0,0) -> 0 | K5: =IFERROR(SUM(H5-I5),H5) -> 0 | L5: =IFERROR(SUM(H5-J5),H5) -> 0
A6: 1001 | B6: CENTRACORE LLC HOUSEHOLD | C6: Julie Jones | D6: 251 | E6: =_xlfn.XLOOKUP(A6,'Current Month'!A:A,'Current Month'!I:I,"") | F6: =_xlfn.XLOOKUP(A6,'Prior Month'!A:A,'Prior Month'!I:I,"") | G6: =_xlfn.XLOOKUP(A6,'Year end 2024'!A:A,'Year end 2024'!I:I,"") | H6: =_xlfn.XLOOKUP(A6,'Current Month'!A:A,'Current Month'!E:E,0,0) -> 220739.22 | I6: =_xlfn.XLOOKUP(A6,'Prior Month'!A:A,'Prior Month'!E:E,0,0) -> 220739.22 | J6: =_xlfn.XLOOKUP(A6,'Year end 2024'!A:A,'Year end 2024'!E:E,0,0) -> 15614.22 | K6: =IFERROR(SUM(H6-I6),H6) -> 0 | L6: =IFERROR(SUM(H6-J6),H6) -> 205125
A7: 1002 | B7: CONSTABLE REAL ESTATE LLC HOUSEHOLD | C7: Marlon Attiq | D7: 459 | E7: =_xlfn.XLOOKUP(A7,'Current Month'!A:A,'Current Month'!I:I,"") | F7: =_xlfn.XLOOKUP(A7,'Prior Month'!A:A,'Prior Month'!I:I,"") | G7: =_xlfn.XLOOKUP(A7,'Year end 2024'!A:A,'Year end 2024'!I:I,"") | H7: =_xlfn.XLOOKUP(A7,'Current Month'!A:A,'Current Month'!E:E,0,0) -> 20688.59 | I7: =_xlfn.XLOOKUP(A7,'Prior Month'!A:A,'Prior Month'!E:E,0,0) -> 32628.17 | J7: =_xlfn.XLOOKUP(A7,'Year end 2024'!A:A,'Year end 2024'!E:E,0,0) -> 32971.55 | K7: =IFERROR(SUM(H7-I7),H7) -> -11939.58 | L7: =IFERROR(SUM(H7-J7),H7) -> -12282.96
A8: 1003 | B8: ELISECO INC & NOVID LLC HOUSEHOLD | C8: Cary Listerman | D8: 130 | E8: =_xlfn.XLOOKUP(A8,'Current Month'!A:A,'Current Month'!I:I,"") | F8: =_xlfn.XLOOKUP(A8,'Prior Month'!A:A,'Prior Month'!I:I,"") | G8: =_xlfn.XLOOKUP(A8,'Year end 2024'!A:A,'Year end 2024'!I:I,"") -> 2.5914041 | H8: =_xlfn.XLOOKUP(A8,'Current Month'!A:A,'Current Month'!E:E,0,0) -> 728270.09 | I8: =_xlfn.XLOOKUP(A8,'Prior Month'!A:A,'Prior Month'!E:E,0,0) -> 728264.62 | J8: =_xlfn.XLOOKUP(A8,'Year end 2024'!A:A,'Year end 2024'!E:E,0,0) -> 1295702 | K8: =IFERROR(SUM(H8-I8),H8) -> 5.47 | L8: =IFERROR(SUM(H8-J8),H8) -> -567431.94
A9: 1007 | B9: KING CARPENTRY LLC HOUSEHOLD | C9: Julie Jones | D9: 251 | E9: =_xlfn.XLOOKUP(A9,'Current Month'!A:A,'Current Month'!I:I,"") | F9: =_xlfn.XLOOKUP(A9,'Prior Month'!A:A,'Prior Month'!I:I,"") | G9: =_xlfn.XLOOKUP(A9,'Year end 2024'!A:A,'Year end 2024'!I:I,"") | H9: =_xlfn.XLOOKUP(A9,'Current Month'!A:A,'Current Month'!E:E,0,0) -> 233578.99 | I9: =_xlfn.XLOOKUP(A9,'Prior Month'!A:A,'Prior Month'!E:E,0,0) -> 233583.99 | J9: =_xlfn.XLOOKUP(A9,'Year end 2024'!A:A,'Year end 2024'!E:E,0,0) -> 233698.99 | K9: =IFERROR(SUM(H9-I9),H9) -> -5 | L9: =IFERROR(SUM(H9-J9),H9) -> -120
A10: 1008 | B10: INTERVENTIONAL PAIN CENTER PLLC HOUSEHOLD | C10: Marlon Attiq | D10: 459 | E10: =_xlfn.XLOOKUP(A10,'Current Month'!A:A,'Current Month'!I:I,"") | F10: =_xlfn.XLOOKUP(A10,'Prior Month'!A:A,'Prior Month'!I:I,"") | G10: =_xlfn.XLOOKUP(A10,'Year end 2024'!A:A,'Year end 2024'!I:I,"") | H10: =_xlfn.XLOOKUP(A10,'Current Month'!A:A,'Current Month'!E:E,0,0) -> 5961.65 | I10: =_xlfn.XLOOKUP(A10,'Prior Month'!A:A,'Prior Month'!E:E,0,0) -> 5961.65 | J10: =_xlfn.XLOOKUP(A10,'Year end 2024'!A:A,'Year end 2024'!E:E,0,0) -> 6031.65 | K10: =IFERROR(SUM(H10-I10),H10) -> 0 | L10: =IFERROR(SUM(H10-J10),H10) -> -70
A11: 1009 | B11: INSPIRED CONCEPTS LLC HOUSEHOLD | C11: Joshua Copen | D11: 453 | E11: =_xlfn.XLOOKUP(A11,'Current Month'!A:A,'Current Month'!I:I,"") | F11: =_xlfn.XLOOKUP(A11,'Prior Month'!A:A,'Prior Month'!I:I,"") | G11: =_xlfn.XLOOKUP(A11,'Year end 2024'!A:A,'Year end 2024'!I:I,"") | H11: =_xlfn.XLOOKUP(A11,'Current Month'!A:A,'Current Month'!E:E,0,0) -> 57558.93 | I11: =_xlfn.XLOOKUP(A11,'Prior Month'!A:A,'Prior Month'!E:E,0,0) -> 45089.47 | J11: =_xlfn.XLOOKUP(A11,'Year end 2024'!A:A,'Year end 2024'!E:E,0,0) -> 57460.44 | K11: =IFERROR(SUM(H11-I11),H11) -> 12469.46 | L11: =IFERROR(SUM(H11-J11),H11) -> 98.49
A12: 101 | B12: Goodrich United Methodist Church Household | C12: Steve Tondreau | D12: 139 | E12: =_xlfn.XLOOKUP(A12,'Current Month'!A:A,'Current Month'!I:I,"") | F12: =_xlfn.XLOOKUP(A12,'Prior Month'!A:A,'Prior Month'!I:I,"") | G12: =_xlfn.XLOOKUP(A12,'Year end 2024'!A:A,'Year end 2024'!I:I,"") -> 11.556422 | H12: =_xlfn.XLOOKUP(A12,'Current Month'!A:A,'Current Month'!E:E,0,0) -> 152500.04 | I12: =_xlfn.XLOOKUP(A12,'Prior Month'!A:A,'Prior Month'!E:E,0,0) -> 181111.2 | J12: =_xlfn.XLOOKUP(A12,'Year end 2024'!A:A,'Year end 2024'!E:E,0,0) -> 142127 | K12: =IFERROR(SUM(H12-I12),H12) -> -28611.16 | L12: =IFERROR(SUM(H12-J12),H12) -> 10373.04
A13: 1010 | B13: THE GLAESER DAWES CORPORATION HOUSEHOLD | C13: Marlon Attiq | D13: 459 | E13: =_xlfn.XLOOKUP(A13,'Current Month'!A:A,'Current Month'!I:I,"") | F13: =_xlfn.XLOOKUP(A13,'Prior Month'!A:A,'Prior Month'!I:I,"") | G13: =_xlfn.XLOOKUP(A13,'Year end 2024'!A:A,'Year end 2024'!I:I,"") | H13: =_xlfn.XLOOKUP(A13,'Current Month'!A:A,'Current Month'!E:E,0,0) -> 2030.78 | I13: =_xlfn.XLOOKUP(A13,'Prior Month'!A:A,'Prior Month'!E:E,0,0) -> 2030.78 | J13: =_xlfn.XLOOKUP(A13,'Year end 2024'!A:A,'Year end 2024'!E:E,0,0) -> 2760.78 | K13: =IFERROR(SUM(H13-I13),H13) -> 0 | L13: =IFERROR(SUM(H13-J13),H13) -> -730
... A1083: 999 | B1083: WOODLINE BUILDING CO INC HOUSEHOLD | C1083: Jennifer Sherby | D1083: 151 | E1083: =_xlfn.XLOOKUP(A1083,'Current Month'!A:A,'Current Month'!I:I,"") | F1083: =_xlfn.XLOOKUP(A1083,'Prior Month'!A:A,'Prior Month'!I:I,"") | G1083: =_xlfn.XLOOKUP(A1083,'Year end 2024'!A:A,'Year end 2024'!I:I,"") | H1083: =_xlfn.XLOOKUP(A1083,'Current Month'!A:A,'Current Month'!E:E,0,0) -> 367433.88 | I1083: =_xlfn.XLOOKUP(A1083,'Prior Month'!A:A,'Prior Month'!E:E,0,0) -> 233391.48 | J1083: =_xlfn.XLOOKUP(A1083,'Year end 2024'!A:A,'Year end 2024'!E:E,0,0) -> 224438.35 | K1083: =IFERROR(SUM(H1083-I1083),H1083) -> 134042.4 | L1083: =IFERROR(SUM(H1083-J1083),H1083) -> 142995.53
A1084: Totals | E1084: =_xlfn.XLOOKUP(A1084,'Current Month'!A:A,'Current Month'!I:I,"") -> 0.87124073 | F1084: =_xlfn.XLOOKUP(A1084,'Prior Month'!A:A,'Prior Month'!I:I,"") -> 0.75685917 | G1084: =_xlfn.XLOOKUP(A1084,'Year end 2024'!A:A,'Year end 2024'!I:I,"") -> 0.75325652 | H1084: =SUM(H2:H1083) -> 5.6680562e+08 | I1084: =SUM(I2:I1083) -> 4.939073e+08 | J1084: =SUM(J2:J1083) -> 4.3826263e+08 | K1084: =SUM(K2:K1083) -> 72898324 | L1084: =SUM(L2:L1083) -> 1.2854299e+08

Sheet Current Month
A1: Household ID | B1: Household Name | C1: Officer Code | D1: Officer Name | E1: Current Balance - Deposit | F1: Current Balance - Loan | G1: Available Balance | H1: Lending Commitment | I1: Deposit to Loan Ratio
A2: 1 | B2: MODERN BOOKKEEPING HOUSEHOLD | C2: Mark Morrison | D2: 615 | E2: 33327940 | F2: 764130.12 | G2: 600000 | H2: =IF(ISBLANK(F2),"",(F2+G2)) -> 1364130.1 | I2: =IF(ISBLANK(F2), "", E2/H2) -> 24.431643
A3: 10 | B3: MARK CHERRY HOUSEHOLD | C3: Brad Kirkland | D3: 618 | E3: 165289.76 | F3: 855812.56 | G3: 350000 | H3: =IF(ISBLANK(F3),"",(F3+G3)) -> 1205812.6 | I3: =IF(ISBLANK(F3), "", E3/H3) -> 0.13707749
A4: 100 | B4: Glenn A Bianchini Household | C4: Julie Jones | D4: 251 | E4: 22867.55 | H4: =IF(ISBLANK(F4),"",(F4+G4)) | I4: =IF(ISBLANK(F4), "", E4/H4)
A5: 1000 | B5: FUEL CELL ESA WCSU LLC HOUSEHOLD | C5: Mark Matheson | D5: 675 | E5: 0 | H5: =IF(ISBLANK(F5),"",(F5+G5)) | I5: =IF(ISBLANK(F5), "", E5/H5)
A6: 1001 | B6: CENTRACORE LLC HOUSEHOLD | C6: Julie Jones | D6: 251 | E6: 220739.22 | H6: =IF(ISBLANK(F6),"",(F6+G6)) | I6: =IF(ISBLANK(F6), "", E6/H6)
A7: 1002 | B7: CONSTABLE REAL ESTATE LLC HOUSEHOLD | C7: Marlon Attiq | D7: 459 | E7: 20688.59 | H7: =IF(ISBLANK(F7),"",(F7+G7)) | I7: =IF(ISBLANK(F7), "", E7/H7)
A8: 1003 | B8: ELISECO INC & NOVID LLC HOUSEHOLD | C8: Cary Listerman | D8: 130 | E8: 728270.09 | H8: =IF(ISBLANK(F8),"",(F8+G8)) | I8: =IF(ISBLANK(F8), "", E8/H8)
A9: 1007 | B9: KING CARPENTRY LLC HOUSEHOLD | C9: Julie Jones | D9: 251 | E9: 233578.99 | H9: =IF(ISBLANK(F9),"",(F9+G9)) | I9: =IF(ISBLANK(F9), "", E9/H9)
A10: 1008 | B10: INTERVENTIONAL PAIN CENTER PLLC HOUSEHOLD | C10: Marlon Attiq | D10: 459 | E10: 5961.65 | H10: =IF(ISBLANK(F10),"",(F10+G10)) | I10: =IF(ISBLANK(F10), "", E10/H10)
A11: 1009 | B11: INSPIRED CONCEPTS LLC HOUSEHOLD | C11: Joshua Copen | D11: 453 | E11: 57558.93 | H11: =IF(ISBLANK(F11),"",(F11+G11)) | I11: =IF(ISBLANK(F11), "", E11/H11)
A12: 101 | B12: Goodrich United Methodist Church Household | C12: Steve Tondreau | D12: 139 | E12: 152500.04 | H12: =IF(ISBLANK(F12),"",(F12+G12)) | I12: =IF(ISBLANK(F12), "", E12/H12)
A13: 1010 | B13: THE GLAESER DAWES CORPORATION HOUSEHOLD | C13: Marlon Attiq | D13: 459 | E13: 2030.78 | H13: =IF(ISBLANK(F13),"",(F13+G13)) | I13: =IF(ISBLANK(F13), "", E13/H13)
A14: 1012 | B14: TIMOTHY P ISRAEL HOUSEHOLD | C14: Beth Arnold | D14: 162 | E14: 32535.81 | F14: 483293.21 | G14: 1776.3 | H14: =IF(ISBLANK(F14),"",(F14+G14)) -> 485069.51 | I14: =IF(ISBLANK(F14), "", E14/H14) -> 0.067074531
A15: 1013 | B15: JEREMY B STURZA HOUSEHOLD | C15: Julie Jones | D15: 251 | E15: 4004.87 | H15: =IF(ISBLANK(F15),"",(F15+G15)) | I15: =IF(ISBLANK(F15), "", E15/H15)
A16: 1014 | B16: DAVID M ROSE HOUSEHOLD | C16: Adrienne Flintoft | D16: 271 | E16: 8312.04 | F16: 40162.42 | G16: 39837.58 | H16: =IF(ISBLANK(F16),"",(F16+G16)) -> 80000 | I16: =IF(ISBLANK(F16), "", E16/H16) -> 0.1039005
A17: 1015 | B17: MARK GESUALE HOUSEHOLD | C17: Joshua Copen | D17: 453 | E17: 2043.06 | F17: 486220.48 | G17: 13779.52 | H17: =IF(ISBLANK(F17),"",(F17+G17)) -> 500000 | I17: =IF(ISBLANK(F17), "", E17/H17) -> 0.00408612
A18: 1016 | B18: SAMUEL D SWEET PLC HOUSEHOLD | C18: Julie Jones | D18: 251 | E18: 5006.72 | F18: 221649.57 | H18: =IF(ISBLANK(F18),"",(F18+G18)) -> 221649.57 | I18: =IF(ISBLANK(F18), "", E18/H18) -> 0.022588449
A19: 1017 | B19: RICHARD A BLASUTIG HOUSEHOLD | C19: Beth Arnold | D19: 162 | E19: 387.53 | F19: 52200.87 | H19: =IF(ISBLANK(F19),"",(F19+G19)) -> 52200.87 | I19: =IF(ISBLANK(F19), "", E19/H19) -> 0.0074238226
A20: 1018 | B20: DIANNE C KMIOTEK HOUSEHOLD | C20: Nicole Curtiss | D20: 475 | E20: 152109.17 | H20: =IF(ISBLANK(F20),"",(F20+G20)) | I20: =IF(ISBLANK(F20), "", E20/H20)
A21: 1020 | B21: CYPRESS RIDGE CONSULTING GROUP LLC HOUSEHOLD | C21: Cary Listerman | D21: 130 | E21: 186.9 | H21: =IF(ISBLANK(F21),"",(F21+G21)) | I21: =IF(ISBLANK(F21), "", E21/H21)
A22: 1024 | B22: LEON D HIEBER JR HOUSEHOLD | C22: Vladislav Peck | D22: 460 | E22: 109473.77 | H22: =IF(ISBLANK(F22),"",(F22+G22)) | I22: =IF(ISBLANK(F22), "", E22/H22)
A23: 103 | B23: FRIENDS OF THE CLARKSTON INDEPENDENCE HOUSEHOLD | C23: Jennifer Sherby | D23: 151 | E23: 65065.61 | H23: =IF(ISBLANK(F23),"",(F23+G23)) | I23: =IF(ISBLANK(F23), "", E23/H23)
A24: 1030 | B24: STUDENT ADVOCACY CENTER OF MICHIGAN INC HOUSEHOLD | C24: Cary Listerman | D24: 130 | E24: 185197.59 | H24: =IF(ISBLANK(F24),"",(F24+G24)) | I24: =IF(ISBLANK(F24), "", E24/H24)
A25: 1032 | B25: MICHELE SHAUGHNESSY HOUSEHOLD | C25: Cary Listerman | D25: 130 | E25: 305229.83 | H25: =IF(ISBLANK(F25),"",(F25+G25)) | I25: =IF(ISBLANK(F25), "", E25/H25)
A26: 1034 | B26: EICHNER REALTY INC HOUSEHOLD | C26: Vladislav Peck | D26: 460 | E26: 26271.27 | H26: =IF(ISBLANK(F26),"",(F26+G26)) | I26: =IF(ISBLANK(F26), "", E26/H26)
A27: 1035 | B27: TMT MANAGEMENT INC HOUSEHOLD | C27: Marlon Attiq | D27: 459 | E27: 858 | H27: =IF(ISBLANK(F27),"",(F27+G27)) | I27: =IF(ISBLANK(F27), "", E27/H27)
A28: 1037 | B28: SUNSHINE FOODS AND WINE LLC HOUSEHOLD | C28: Vladislav Peck | D28: 460 | E28: 3773.67 | H28: =IF(ISBLANK(F28),"",(F28+G28)) | I28: =IF(ISBLANK(F28), "", E28/H28)
A29: 1039 | B29: TEKSOFT SYSTEMS INC HOUSEHOLD | C29: Julie Jones | D29: 251 | E29: 2084.15 | H29: =IF(ISBLANK(F29),"",(F29+G29)) | I29: =IF(ISBLANK(F29), "", E29/H29)
A30: 104 | B30: Independence Dental PC Household | C30: Marlon Attiq | D30: 459 | E30: 2738.09 | F30: 40014.85 | H30: =IF(ISBLANK(F30),"",(F30+G30)) -> 40014.85 | I30: =IF(ISBLANK(F30), "", E30/H30) -> 0.068426847
A31: 1040 | B31: SANDBEAR EXPRESS INC HOUSEHOLD | C31: Marlon Attiq | D31: 459 | E31: 8.03 | H31: =IF(ISBLANK(F31),"",(F31+G31)) | I31: =IF(ISBLANK(F31), "", E31/H31)
A32: 1043 | B32: CSV RESTAURANTS LLC HOUSEHOLD | C32: Julie Jones | D32: 251 | E32: 227.52 | H32: =IF(ISBLANK(F32),"",(F32+G32)) | I32: =IF(ISBLANK(F32), "", E32/H32)
A33: 1044 | B33: STRATEGIC SERVICES GROUP INC HOUSEHOLD | C33: Joshua Copen | D33: 453 | E33: 267819.74 | H33: =IF(ISBLANK(F33),"",(F33+G33)) | I33: =IF(ISBLANK(F33), "", E33/H33)
A34: 1045 | B34: PAINT CREEK MGMT LLC HOUSEHOLD | C34: Thomas Merrill | D34: 640 | E34: 2141560.4 | F34: 1713695.1 | H34: =IF(ISBLANK(F34),"",(F34+G34)) -> 1713695.1 | I34: =IF(ISBLANK(F34), "", E34/H34) -> 1.2496741
A35: 1046 | B35: MORTGAGE RESOURCE PLUS, INC HOUSEHOLD | C35: Thomas Merrill | D35: 640 | E35: 632211.49 | H35: =IF(ISBLANK(F35),"",(F35+G35)) | I35: =IF(ISBLANK(F35), "", E35/H35)
A36: 1047 | B36: LOVE INC OF NORTH OAKLAND COUNTY HOUSEHOLD | C36: Marlon Attiq | D36: 459 | E36: 37346.59 | H36: =IF(ISBLANK(F36),"",(F36+G36)) | I36: =IF(ISBLANK(F36), "", E36/H36)
A37: 105 | B37: CONSOLIDATED MEDICAL BILLING LLC HOUSEHOLD | C37: Taylor Spicer | D37: 467 | E37: 110593.52 | H37: =IF(ISBLANK(F37),"",(F37+G37)) | I37: =IF(ISBLANK(F37), "", E37/H37)
A38: 1050 | B38: MICHIGAN STRATEGIC FUND HOUSEHOLD | C38: Cary Listerman | D38: 130 | E38: 7773376.3 | H38: =IF(ISBLANK(F38),"",(F38+G38)) | I38: =IF(ISBLANK(F38), "", E38/H38)
A39: 1052 | B39: MRA PROPERTIES LLC HOUSEHOLD | C39: Brad Kirkland | D39: 618 | E39: 342320.23 | F39: 0 | G39: 100000 | H39: =IF(ISBLANK(F39),"",(F39+G39)) -> 100000 | I39: =IF(ISBLANK(F39), "", E39/H39) -> 3.4232023
A40: 1053 | B40: DALE WELSH HOUSEHOLD | C40: Julie Jones | D40: 251 | E40: 340.72 | H40: =IF(ISBLANK(F40),"",(F40+G40)) | I40: =IF(ISBLANK(F40), "", E40/H40)
A41: 1054 | B41: GNS MANAGEMENT LLC HOUSEHOLD | C41: Jennifer Sherby | D41: 151 | E41: 1212.2 | F41: 0 | G41: 200000 | H41: =IF(ISBLANK(F41),"",(F41+G41)) -> 200000 | I41: =IF(ISBLANK(F41), "", E41/H41) -> 0.006061
A42: 1055 | B42: KEVIN CORBIN HOUSEHOLD | C42: Lisa Goldsworthy | D42: 708 | E42: 286.32 | F42: 156129.01 | H42: =IF(ISBLANK(F42),"",(F42+G42)) -> 156129.01 | I42: =IF(ISBLANK(F42), "", E42/H42) -> 0.001833868
A43: 1056 | B43: BURINGTON GOLF CAR RENTALS INC HOUSEHOLD | C43: Cary Listerman | D43: 130 | E43: 3145.28 | F43: 155231.25 | H43: =IF(ISBLANK(F43),"",(F43+G43)) -> 155231.25 | I43: =IF(ISBLANK(F43), "", E43/H43) -> 0.0202619
A44: 1057 | B44: GREGORY WECKLE HOUSEHOLD | C44: Julie Jones | D44: 251 | E44: 755.84 | F44: 227026.44 | G44: 27550 | H44: =IF(ISBLANK(F44),"",(F44+G44)) -> 254576.44 | I44: =IF(ISBLANK(F44), "", E44/H44) -> 0.00296901
A45: 1058 | B45: DBA GENO & SON PROPERTY MANAGEMENT HOUSEHOLD | C45: Julie Jones | D45: 251 | E45: 12070.15 | F45: 148580.03 | G45: 1300 | H45: =IF(ISBLANK(F45),"",(F45+G45)) -> 149880.03 | I45: =IF(ISBLANK(F45), "", E45/H45) -> 0.080532076
A46: 1059 | B46: MICROTECH SYSTEMS INC HOUSEHOLD | C46: Adrienne Flintoft | D46: 271 | E46: 9198.82 | F46: 139288.77 | H46: =IF(ISBLANK(F46),"",(F46+G46)) -> 139288.77 | I46: =IF(ISBLANK(F46), "", E46/H46) -> 0.066041361
A47: 1061 | B47: EUGENE MEAGHER HOUSEHOLD | C47: Julie Jones | D47: 251 | E47: 177.18 | H47: =IF(ISBLANK(F47),"",(F47+G47)) | I47: =IF(ISBLANK(F47), "", E47/H47)
A48: 1062 | B48: MARK HAGEMEISTER HOUSEHOLD | C48: Beth Arnold | D48: 162 | E48: 205.67 | F48: 135826.36 | G48: 1173.64 | H48: =IF(ISBLANK(F48),"",(F48+G48)) -> 137000 | I48: =IF(ISBLANK(F48), "", E48/H48) -> 0.0015012409
A49: 1063 | B49: TRAVELING TRAINER LLC HOUSEHOLD | C49: Beth Arnold | D49: 162 | E49: -288.48 | F49: 118560.39 | H49: =IF(ISBLANK(F49),"",(F49+G49)) -> 118560.39 | I49: =IF(ISBLANK(F49), "", E49/H49) -> -0.0024331904
A50: 1065 | B50: AB INC HOUSEHOLD | C50: Beth Arnold | D50: 162 | E50: 64086.83 | H50: =IF(ISBLANK(F50),"",(F50+G50)) | I50: =IF(ISBLANK(F50), "", E50/H50)
A51: 1066 | B51: ADE INCORPORATED HOUSEHOLD | C51: Jennifer Sherby | D51: 151 | E51: 104546.2 | H51: =IF(ISBLANK(F51),"",(F51+G51)) | I51: =IF(ISBLANK(F51), "", E51/H51)
A52: 1067 | B52: ACCENT ON ART HOUSEHOLD | C52: Adrienne Flintoft | D52: 271 | E52: 24177.54 | H52: =IF(ISBLANK(F52),"",(F52+G52)) | I52: =IF(ISBLANK(F52), "", E52/H52)
A53: 1068 | B53: ADDISON TOWNSHIP LIBRARY HOUSEHOLD | C53: Beth Arnold | D53: 162 | E53: 120746.65 | H53: =IF(ISBLANK(F53),"",(F53+G53)) | I53: =IF(ISBLANK(F53), "", E53/H53)
A54: 1069 | B54: AMERICAN LEGION HOUSEHOLD | C54: Julie Jones | D54: 251 | E54: 224672.72 | F54: 0 | G54: 2500 | H54: =IF(ISBLANK(F54),"",(F54+G54)) -> 2500 | I54: =IF(ISBLANK(F54), "", E54/H54) -> 89.869088
A55: 107 | B55: Jidas Custom Homes Inc Household | C55: Julie Jones | D55: 251 | E55: 332073.3 | F55: 502.9 | G55: 497.1 | H55: =IF(ISBLANK(F55),"",(F55+G55)) -> 1000 | I55: =IF(ISBLANK(F55), "", E55/H55) -> 332.0733
A56: 1070 | B56: ABSOLUTE GREEN CORPORATION HOUSEHOLD | C56: Jennifer Sherby | D56: 151 | E56: 31011.4 | F56: 58402.04 | G56: 191597.96 | H56: =IF(ISBLANK(F56),"",(F56+G56)) -> 250000 | I56: =IF(ISBLANK(F56), "", E56/H56) -> 0.1240456
A57: 1071 | B57: ADVANCE SCRAPING CO HOUSEHOLD | C57: Julie Jones | D57: 251 | E57: 16494.84 | H57: =IF(ISBLANK(F57),"",(F57+G57)) | I57: =IF(ISBLANK(F57), "", E57/H57)
A58: 1072 | B58: DENNIS ASHTON HOUSEHOLD | C58: Taylor Spicer | D58: 467 | E58: 115343.22 | H58: =IF(ISBLANK(F58),"",(F58+G58)) | I58: =IF(ISBLANK(F58), "", E58/H58)
A59: 1073 | B59: ADDISON PLUMBING CO HOUSEHOLD | C59: Beth Arnold | D59: 162 | E59: 315066.85 | H59: =IF(ISBLANK(F59),"",(F59+G59)) | I59: =IF(ISBLANK(F59), "", E59/H59)
A60: 1074 | B60: ALL SPORTS BRANDON BOOSTERS HOUSEHOLD | C60: Taylor Spicer | D60: 467 | E60: 29656.18 | H60: =IF(ISBLANK(F60),"",(F60+G60)) | I60: =IF(ISBLANK(F60), "", E60/H60)
A61: 1075 | B61: ALMONT AREA SENIOR CITIZENS HOUSEHOLD | C61: Beth Arnold | D61: 162 | E61: 12793.21 | H61: =IF(ISBLANK(F61),"",(F61+G61)) | I61: =IF(ISBLANK(F61), "", E61/H61)
A62: 1076 | B62: ADDISON TWP FIREFIGHTERS ASSOC HOUSEHOLD | C62: Julie Jones | D62: 251 | E62: 41804.25 | H62: =IF(ISBLANK(F62),"",(F62+G62)) | I62: =IF(ISBLANK(F62), "", E62/H62)
A63: 1077 | B63: ALMONT DRYDEN LODGE NO 51 HOUSEHOLD | C63: Beth Arnold | D63: 162 | E63: 17357.13 | H63: =IF(ISBLANK(F63),"",(F63+G63)) | I63: =IF(ISBLANK(F63), "", E63/H63)
A64: 1078 | B64: ADDISON MEADOWS ASSOCIATION HOUSEHOLD | C64: Beth Arnold | D64: 162 | E64: 7651.16 | H64: =IF(ISBLANK(F64),"",(F64+G64)) | I64: =IF(ISBLANK(F64), "", E64/H64)
A65: 1079 | B65: AARON ENGLER CERTIFIED FARRIER INC HOUSEHOLD | C65: Beth Arnold | D65: 162 | E65: 154088.25 | H65: =IF(ISBLANK(F65),"",(F65+G65)) | I65: =IF(ISBLANK(F65), "", E65/H65)
A66: 108 | B66: John Hicks Household | C66: Beth Arnold | D66: 162 | E66: 1293.89 | H66: =IF(ISBLANK(F66),"",(F66+G66)) | I66: =IF(ISBLANK(F66), "", E66/H66)
A67: 1080 | B67: AMELL INC HOUSEHOLD | C67: Beth Arnold | D67: 162 | E67: 351751.02 | H67: =IF(ISBLANK(F67),"",(F67+G67)) | I67: =IF(ISBLANK(F67), "", E67/H67)
A68: 1081 | B68: GARY AHLBERG HOUSEHOLD | C68: Beth Arnold | D68: 162 | E68: 32128.04 | H68: =IF(ISBLANK(F68),"",(F68+G68)) | I68: =IF(ISBLANK(F68), "", E68/H68)
... A72: 1085 | B72: GRAZING LIFE LLC HOUSEHOLD | C72: Beth Arnold | D72: 162 | E72: 236340.52 | H72: =IF(ISBLANK(F72),"",(F72+G72)) | I72: =IF(ISBLANK(F72), "", E72/H72)
A73: 1086 | B73: MA MANAGEMENT GROUP HOUSEHOLD | C73: Claire Marie Spencer | D73: 478 | E73: 4815.37 | F73: 336675.82 | H73: =IF(ISBLANK(F73),"",(F73+G73)) -> 336675.82 | I73: =IF(ISBLANK(F73), "", E73/H73) -> 0.01430269
A74: 1087 | B74: VALOR SALON HOUSEHOLD | C74: Julie Jones | D74: 251 | E74: 3991.07 | F74: 542136.54 | G74: 85363.46 | H74: =IF(ISBLANK(F74),"",(F74+G74)) -> 627500 | I74: =IF(ISBLANK(F74), "", E74/H74) -> 0.0063602709
A75: 1088 | B75: HAINES DRAINS HOUSEHOLD | C75: Jennifer Sherby | D75: 151 | E75: 1182.82 | F75: 254516.93 | G75: 583.91 | H75: =IF(ISBLANK(F75),"",(F75+G75)) -> 255100.84 | I75: =IF(ISBLANK(F75), "", E75/H75) -> 0.0046366762
A76: 1089 | B76: AMANDA GRAIN COMPANY HOUSEHOLD | C76: Beth Arnold | D76: 162 | E76: 35189.07 | H76: =IF(ISBLANK(F76),"",(F76+G76)) | I76: =IF(ISBLANK(F76), "", E76/H76)
A77: 109 | B77: Karen Mersino Household | C77: Brad Kirkland | D77: 618 | E77: 1324732.1 | F77: 206760.95 | G77: 294239.05 | H77: =IF(ISBLANK(F77),"",(F77+G77)) -> 501000 | I77: =IF(ISBLANK(F77), "", E77/H77) -> 2.6441759
A78: 1090 | B78: AQUA HEATING AND COOLING LLC HOUSEHOLD | C78: Julie Jones | D78: 251 | E78: 869103.75 | H78: =IF(ISBLANK(F78),"",(F78+G78)) | I78: =IF(ISBLANK(F78), "", E78/H78)
A79: 1091 | B79: A & D PRODUCTS LLC HOUSEHOLD | C79: Beth Arnold | D79: 162 | E79: 23998.21 | H79: =IF(ISBLANK(F79),"",(F79+G79)) | I79: =IF(ISBLANK(F79), "", E79/H79)
A80: 1092 | B80: A & G INVESTMENT PROPERTIES LTD HOUSEHOLD | C80: Taylor Spicer | D80: 467 | E80: 44528.1 | H80: =IF(ISBLANK(F80),"",(F80+G80)) | I80: =IF(ISBLANK(F80), "", E80/H80)
A81: 1093 | B81: DAVID BLOCKI HOUSEHOLD | C81: Beth Arnold | D81: 162 | E81: 73008.31 | H81: =IF(ISBLANK(F81),"",(F81+G81)) | I81: =IF(ISBLANK(F81), "", E81/H81)
A82: 1095 | B82: ALLEN DRESSAGE INC HOUSEHOLD | C82: Julie Jones | D82: 251 | E82: 73948.04 | H82: =IF(ISBLANK(F82),"",(F82+G82)) | I82: =IF(ISBLANK(F82), "", E82/H82)
A83: 1096 | B83: AURSAM PROPERTY SERVICES LLC HOUSEHOLD | C83: Julie Jones | D83: 251 | E83: 41189.98 | H83: =IF(ISBLANK(F83),"",(F83+G83)) | I83: =IF(ISBLANK(F83), "", E83/H83)
A84: 1098 | B84: ALIFETIME OF EVERYTHING LLC HOUSEHOLD | C84: Beth Arnold | D84: 162 | E84: 601.93 | H84: =IF(ISBLANK(F84),"",(F84+G84)) | I84: =IF(ISBLANK(F84), "", E84/H84)
A85: 11 | B85: NCG CINEMAS HOUSEHOLD | C85: Brad Kirkland | D85: 618 | E85: 638439.52 | F85: 8163644.7 | G85: 0 | H85: =IF(ISBLANK(F85),"",(F85+G85)) -> 8163644.7 | I85: =IF(ISBLANK(F85), "", E85/H85) -> 0.078205207
A86: 110 | B86: KC'S DAIRY TWIST HOUSEHOLD | C86: Jack Korth | D86: 653 | E86: 71.73 | F86: 12304.29 | H86: =IF(ISBLANK(F86),"",(F86+G86)) -> 12304.29 | I86: =IF(ISBLANK(F86), "", E86/H86) -> 0.005829674
A87: 1100 | B87: ALPHABET CARPENTRY INC HOUSEHOLD | C87: Beth Arnold | D87: 162 | E87: 29035.5 | H87: =IF(ISBLANK(F87),"",(F87+G87)) | I87: =IF(ISBLANK(F87), "", E87/H87)
A88: 1101 | B88: PAMELA ALEXANDER HOUSEHOLD | C88: Nicole Curtiss | D88: 475 | E88: 24672.57 | H88: =IF(ISBLANK(F88),"",(F88+G88)) | I88: =IF(ISBLANK(F88), "", E88/H88)
A89: 1102 | B89: ATLEE MILLER FARRIER SERVICE LLC HOUSEHOLD | C89: Beth Arnold | D89: 162 | E89: 25728.35 | H89: =IF(ISBLANK(F89),"",(F89+G89)) | I89: =IF(ISBLANK(F89), "", E89/H89)
A90: 1103 | B90: AMERICAN CUTTING LLC HOUSEHOLD | C90: Beth Arnold | D90: 162 | E90: 30267.78 | H90: =IF(ISBLANK(F90),"",(F90+G90)) | I90: =IF(ISBLANK(F90), "", E90/H90)
A91: 1107 | B91: ACORN INDUSTRIES HOUSEHOLD | C91: Nicole Curtiss | D91: 475 | E91: 3169.7 | H91: =IF(ISBLANK(F91),"",(F91+G91)) | I91: =IF(ISBLANK(F91), "", E91/H91)
A92: 1108 | B92: WAYNE SLUITER HOUSEHOLD | C92: Nicole Curtiss | D92: 475 | E92: 1443.15 | H92: =IF(ISBLANK(F92),"",(F92+G92)) | I92: =IF(ISBLANK(F92), "", E92/H92)
A93: 1109 | B93: ADVANCED REMODELING & CONSTRUCTION LLC HOUSEHOLD | C93: Beth Arnold | D93: 162 | E93: 16283.06 | H93: =IF(ISBLANK(F93),"",(F93+G93)) | I93: =IF(ISBLANK(F93), "", E93/H93)
A94: 111 | B94: KENNETH LATSHAW HOUSEHOLD | C94: Adrienne Flintoft | D94: 271 | E94: 2114219.7 | F94: 15282.26 | G94: 34717.74 | H94: =IF(ISBLANK(F94),"",(F94+G94)) -> 50000 | I94: =IF(ISBLANK(F94), "", E94/H94) -> 42.284394
A95: 1110 | B95: NJ GALLAGHER CONTRACTOR LLC HOUSEHOLD | C95: Marlon Attiq | D95: 459 | E95: 109119.61 | H95: =IF(ISBLANK(F95),"",(F95+G95)) | I95: =IF(ISBLANK(F95), "", E95/H95)
A96: 1111 | B96: ROSATI MASON CONTRACTORS LLC HOUSEHOLD | C96: Jennifer Sherby | D96: 151 | E96: 960908.32 | H96: =IF(ISBLANK(F96),"",(F96+G96)) | I96: =IF(ISBLANK(F96), "", E96/H96)
A97: 1112 | B97: DENNIS INGLES & SONS EXCAVATING LLC HOUSEHOLD | C97: Taylor Spicer | D97: 467 | E97: 154607.28 | H97: =IF(ISBLANK(F97),"",(F97+G97)) | I97: =IF(ISBLANK(F97), "", E97/H97)
A98: 1113 | B98: JON M GASKELL HOUSEHOLD | C98: Jennifer Sherby | D98: 151 | E98: 31602.46 | H98: =IF(ISBLANK(F98),"",(F98+G98)) | I98: =IF(ISBLANK(F98), "", E98/H98)
A99: 1114 | B99: GOODLOE BROTHERS LLC HOUSEHOLD | C99: Julie Jones | D99: 251 | E99: 7251.33 | H99: =IF(ISBLANK(F99),"",(F99+G99)) | I99: =IF(ISBLANK(F99), "", E99/H99)
A100: 1117 | B100: GLORIFIED INVESTMENT GROUP LLC HOUSEHOLD | C100: Jennifer Sherby | D100: 151 | E100: 2187.15 | H100: =IF(ISBLANK(F100),"",(F100+G100)) | I100: =IF(ISBLANK(F100), "", E100/H100)
A101: 1118 | B101: GOOD HANGS LLC HOUSEHOLD | C101: Julie Jones | D101: 251 | E101: 28874.87 | H101: =IF(ISBLANK(F101),"",(F101+G101)) | I101: =IF(ISBLANK(F101), "", E101/H101)
A102: 1119 | B102: GIRLS SCOUTS OF SOUTH EASTERN MI 78024 HOUSEHOLD | C102: Taylor Spicer | D102: 467 | E102: 4650.04 | H102: =IF(ISBLANK(F102),"",(F102+G102)) | I102: =IF(ISBLANK(F102), "", E102/H102)
A103: 1121 | B103: GREAT LAKES HEARING CARE LLC HOUSEHOLD | C103: Marlon Attiq | D103: 459 | E103: 232113.98 | H103: =IF(ISBLANK(F103),"",(F103+G103)) | I103: =IF(ISBLANK(F103), "", E103/H103)
...

Sheet Prior Month
A1: Household ID | B1: Household Name | C1: Officer Code | D1: Officer Name | E1: Current Balance - Deposit | F1: Current Balance - Loan | G1: Available Balance | H1: Total Lending | I1: Ratio
A2: 1 | B2: MODERN BOOKKEEPING HOUSEHOLD | C2: Mark Morrison | D2: 615 | E2: 34935884 | F2: 766345.83 | G2: 600000 | H2: =IF(ISBLANK(F2), "",(F2+G2)) -> 1366345.8 | I2: =IF(ISBLANK(F2), "", E2/H2) -> 25.568844
A3: 10 | B3: MARK CHERRY HOUSEHOLD | C3: Brad Kirkland | D3: 618 | E3: 132546.61 | F3: 862284.42 | G3: 350000 | H3: =IF(ISBLANK(F3), "",(F3+G3)) -> 1212284.4 | I3: =IF(ISBLANK(F3), "", E3/H3) -> 0.10933623
A4: 100 | B4: Glenn A Bianchini Household | C4: Julie Jones | D4: 251 | E4: 23748.96 | H4: =IF(ISBLANK(F4), "",(F4+G4)) | I4: =IF(ISBLANK(F4), "", E4/H4)
A5: 1000 | B5: FUEL CELL ESA WCSU LLC HOUSEHOLD | C5: Mark Matheson | D5: 675 | E5: 0 | H5: =IF(ISBLANK(F5), "",(F5+G5)) | I5: =IF(ISBLANK(F5), "", E5/H5)
A6: 1001 | B6: CENTRACORE LLC HOUSEHOLD | C6: Julie Jones | D6: 251 | E6: 220739.22 | H6: =IF(ISBLANK(F6), "",(F6+G6)) | I6: =IF(ISBLANK(F6), "", E6/H6)
A7: 1002 | B7: CONSTABLE REAL ESTATE LLC HOUSEHOLD | C7: Marlon Attiq | D7: 459 | E7: 32628.17 | H7: =IF(ISBLANK(F7), "",(F7+G7)) | I7: =IF(ISBLANK(F7), "", E7/H7)
A8: 1003 | B8: ELISECO INC & NOVID LLC HOUSEHOLD | C8: Cary Listerman | D8: 130 | E8: 728264.62 | H8: =IF(ISBLANK(F8), "",(F8+G8)) | I8: =IF(ISBLANK(F8), "", E8/H8)
A9: 1007 | B9: KING CARPENTRY LLC HOUSEHOLD | C9: Julie Jones | D9: 251 | E9: 233583.99 | H9: =IF(ISBLANK(F9), "",(F9+G9)) | I9: =IF(ISBLANK(F9), "", E9/H9)
A10: 1008 | B10: INTERVENTIONAL PAIN CENTER PLLC HOUSEHOLD | C10: Marlon Attiq | D10: 459 | E10: 5961.65 | H10: =IF(ISBLANK(F10), "",(F10+G10)) | I10: =IF(ISBLANK(F10), "", E10/H10)
A11: 1009 | B11: INSPIRED CONCEPTS LLC HOUSEHOLD | C11: Joshua Copen | D11: 453 | E11: 45089.47 | H11: =IF(ISBLANK(F11), "",(F11+G11)) | I11: =IF(ISBLANK(F11), "", E11/H11)
A12: 101 | B12: Goodrich United Methodist Church Household | C12: Steve Tondreau | D12: 139 | E12: 181111.2 | H12: =IF(ISBLANK(F12), "",(F12+G12)) | I12: =IF(ISBLANK(F12), "", E12/H12)
A13: 1010 | B13: THE GLAESER DAWES CORPORATION HOUSEHOLD | C13: Marlon Attiq | D13: 459 | E13: 2030.78 | H13: =IF(ISBLANK(F13), "",(F13+G13)) | I13: =IF(ISBLANK(F13), "", E13/H13)
A14: 1012 | B14: TIMOTHY P ISRAEL HOUSEHOLD | C14: Beth Arnold | D14: 162 | E14: 35284.8 | F14: 485089.91 | G14: 792.07 | H14: =IF(ISBLANK(F14), "",(F14+G14)) -> 485881.98 | I14: =IF(ISBLANK(F14), "", E14/H14) -> 0.072620104
A15: 1013 | B15: JEREMY B STURZA HOUSEHOLD | C15: Julie Jones | D15: 251 | E15: 3565.5 | H15: =IF(ISBLANK(F15), "",(F15+G15)) | I15: =IF(ISBLANK(F15), "", E15/H15)
A16: 1014 | B16: DAVID M ROSE HOUSEHOLD | C16: Adrienne Flintoft | D16: 271 | E16: 11513.41 | F16: 336101.06 | G16: 30023.39 | H16: =IF(ISBLANK(F16), "",(F16+G16)) -> 366124.45 | I16: =IF(ISBLANK(F16), "", E16/H16) -> 0.031446712
A17: 1015 | B17: MARK GESUALE HOUSEHOLD | C17: Joshua Copen | D17: 453 | E17: 1277.31 | F17: 482761.36 | G17: 17238.64 | H17: =IF(ISBLANK(F17), "",(F17+G17)) -> 500000 | I17: =IF(ISBLANK(F17), "", E17/H17) -> 0.00255462
A18: 1016 | B18: SAMUEL D SWEET PLC HOUSEHOLD | C18: Julie Jones | D18: 251 | E18: 8144.99 | F18: 222662.45 | H18: =IF(ISBLANK(F18), "",(F18+G18)) -> 222662.45 | I18: =IF(ISBLANK(F18), "", E18/H18) -> 0.036579989
A19: 1017 | B19: RICHARD A BLASUTIG HOUSEHOLD | C19: Beth Arnold | D19: 162 | E19: 336.65 | F19: 53824.25 | H19: =IF(ISBLANK(F19), "",(F19+G19)) -> 53824.25 | I19: =IF(ISBLANK(F19), "", E19/H19) -> 0.0062546157
A20: 1018 | B20: DIANNE C KMIOTEK HOUSEHOLD | C20: Nicole Curtiss | D20: 475 | E20: 147015.11 | H20: =IF(ISBLANK(F20), "",(F20+G20)) | I20: =IF(ISBLANK(F20), "", E20/H20)
A21: 1020 | B21: CYPRESS RIDGE CONSULTING GROUP LLC HOUSEHOLD | C21: Cary Listerman | D21: 130 | E21: 196.9 | H21: =IF(ISBLANK(F21), "",(F21+G21)) | I21: =IF(ISBLANK(F21), "", E21/H21)
A22: 1024 | B22: LEON D HIEBER JR HOUSEHOLD | C22: Vladislav Peck | D22: 460 | E22: 109106.1 | H22: =IF(ISBLANK(F22), "",(F22+G22)) | I22: =IF(ISBLANK(F22), "", E22/H22)
A23: 103 | B23: FRIENDS OF THE CLARKSTON INDEPENDENCE HOUSEHOLD | C23: Jennifer Sherby | D23: 151 | E23: 66169.49 | H23: =IF(ISBLANK(F23), "",(F23+G23)) | I23: =IF(ISBLANK(F23), "", E23/H23)
A24: 1030 | B24: STUDENT ADVOCACY CENTER OF MICHIGAN INC HOUSEHOLD | C24: Cary Listerman | D24: 130 | E24: 184605.58 | H24: =IF(ISBLANK(F24), "",(F24+G24)) | I24: =IF(ISBLANK(F24), "", E24/H24)
A25: 1032 | B25: MICHELE SHAUGHNESSY HOUSEHOLD | C25: Cary Listerman | D25: 130 | E25: 304204.7 | H25: =IF(ISBLANK(F25), "",(F25+G25)) | I25: =IF(ISBLANK(F25), "", E25/H25)
A26: 1034 | B26: EICHNER REALTY INC HOUSEHOLD | C26: Vladislav Peck | D26: 460 | E26: 70705.06 | H26: =IF(ISBLANK(F26), "",(F26+G26)) | I26: =IF(ISBLANK(F26), "", E26/H26)
A27: 1035 | B27: TMT MANAGEMENT INC HOUSEHOLD | C27: Marlon Attiq | D27: 459 | E27: 858 | H27: =IF(ISBLANK(F27), "",(F27+G27)) | I27: =IF(ISBLANK(F27), "", E27/H27)
A28: 1037 | B28: SUNSHINE FOODS AND WINE LLC HOUSEHOLD | C28: Vladislav Peck | D28: 460 | E28: 3803.67 | H28: =IF(ISBLANK(F28), "",(F28+G28)) | I28: =IF(ISBLANK(F28), "", E28/H28)
A29: 1039 | B29: TEKSOFT SYSTEMS INC HOUSEHOLD | C29: Julie Jones | D29: 251 | E29: 2089.15 | H29: =IF(ISBLANK(F29), "",(F29+G29)) | I29: =IF(ISBLANK(F29), "", E29/H29)
A30: 104 | B30: Independence Dental PC Household | C30: Marlon Attiq | D30: 459 | E30: 2744.88 | F30: 42743.89 | H30: =IF(ISBLANK(F30), "",(F30+G30)) -> 42743.89 | I30: =IF(ISBLANK(F30), "", E30/H30) -> 0.064216897
A31: 1040 | B31: SANDBEAR EXPRESS INC HOUSEHOLD | C31: Marlon Attiq | D31: 459 | E31: 8.03 | H31: =IF(ISBLANK(F31), "",(F31+G31)) | I31: =IF(ISBLANK(F31), "", E31/H31)
A32: 1043 | B32: CSV RESTAURANTS LLC HOUSEHOLD | C32: Julie Jones | D32: 251 | E32: 776.89 | H32: =IF(ISBLANK(F32), "",(F32+G32)) | I32: =IF(ISBLANK(F32), "", E32/H32)
A33: 1044 | B33: STRATEGIC SERVICES GROUP INC HOUSEHOLD | C33: Joshua Copen | D33: 453 | E33: 162676.32 | H33: =IF(ISBLANK(F33), "",(F33+G33)) | I33: =IF(ISBLANK(F33), "", E33/H33)
A34: 1045 | B34: PAINT CREEK MGMT LLC HOUSEHOLD | C34: Thomas Merrill | D34: 640 | E34: 2115363 | F34: 1720950.9 | H34: =IF(ISBLANK(F34), "",(F34+G34)) -> 1720950.9 | I34: =IF(ISBLANK(F34), "", E34/H34) -> 1.2291827
A35: 1046 | B35: MORTGAGE RESOURCE PLUS, INC HOUSEHOLD | C35: Thomas Merrill | D35: 640 | E35: 583650.25 | H35: =IF(ISBLANK(F35), "",(F35+G35)) | I35: =IF(ISBLANK(F35), "", E35/H35)
A36: 1047 | B36: LOVE INC OF NORTH OAKLAND COUNTY HOUSEHOLD | C36: Marlon Attiq | D36: 459 | E36: 37653.84 | H36: =IF(ISBLANK(F36), "",(F36+G36)) | I36: =IF(ISBLANK(F36), "", E36/H36)
A37: 105 | B37: CONSOLIDATED MEDICAL BILLING LLC HOUSEHOLD | C37: Taylor Spicer | D37: 467 | E37: 87576.48 | H37: =IF(ISBLANK(F37), "",(F37+G37)) | I37: =IF(ISBLANK(F37), "", E37/H37)
A38: 1050 | B38: MICHIGAN STRATEGIC FUND HOUSEHOLD | C38: Cary Listerman | D38: 130 | E38: 7765155 | H38: =IF(ISBLANK(F38), "",(F38+G38)) | I38: =IF(ISBLANK(F38), "", E38/H38)
A39: 1052 | B39: MRA PROPERTIES LLC HOUSEHOLD | C39: Brad Kirkland | D39: 618 | E39: 212050.34 | F39: 0 | G39: 100000 | H39: =IF(ISBLANK(F39), "",(F39+G39)) -> 100000 | I39: =IF(ISBLANK(F39), "", E39/H39) -> 2.1205034
A40: 1053 | B40: DALE WELSH HOUSEHOLD | C40: Julie Jones | D40: 251 | E40: 340.65 | H40: =IF(ISBLANK(F40), "",(F40+G40)) | I40: =IF(ISBLANK(F40), "", E40/H40)
A41: 1054 | B41: GNS MANAGEMENT LLC HOUSEHOLD | C41: Jennifer Sherby | D41: 151 | E41: 74.82 | F41: 0 | G41: 200000 | H41: =IF(ISBLANK(F41), "",(F41+G41)) -> 200000 | I41: =IF(ISBLANK(F41), "", E41/H41) -> 0.0003741
A42: 1055 | B42: KEVIN CORBIN HOUSEHOLD | C42: Lisa Goldsworthy | D42: 708 | E42: 324.43 | F42: 156927.92 | H42: =IF(ISBLANK(F42), "",(F42+G42)) -> 156927.92 | I42: =IF(ISBLANK(F42), "", E42/H42) -> 0.0020673823
A43: 1056 | B43: BURINGTON GOLF CAR RENTALS INC HOUSEHOLD | C43: Cary Listerman | D43: 130 | E43: 2880.32 | F43: 155718.07 | H43: =IF(ISBLANK(F43), "",(F43+G43)) -> 155718.07 | I43: =IF(ISBLANK(F43), "", E43/H43) -> 0.018497018
A44: 1057 | B44: GREGORY WECKLE HOUSEHOLD | C44: Julie Jones | D44: 251 | E44: 266.45 | F44: 226370.45 | G44: 28550 | H44: =IF(ISBLANK(F44), "",(F44+G44)) -> 254920.45 | I44: =IF(ISBLANK(F44), "", E44/H44) -> 0.001045228
A45: 1058 | B45: DBA GENO & SON PROPERTY MANAGEMENT HOUSEHOLD | C45: Julie Jones | D45: 251 | E45: 8301.4 | F45: 148580.03 | G45: 1300 | H45: =IF(ISBLANK(F45), "",(F45+G45)) -> 149880.03 | I45: =IF(ISBLANK(F45), "", E45/H45) -> 0.055386965
A46: 1059 | B46: MICROTECH SYSTEMS INC HOUSEHOLD | C46: Adrienne Flintoft | D46: 271 | E46: 12669.41 | F46: 141546.06 | H46: =IF(ISBLANK(F46), "",(F46+G46)) -> 141546.06 | I46: =IF(ISBLANK(F46), "", E46/H46) -> 0.089507331
A47: 1061 | B47: EUGENE MEAGHER HOUSEHOLD | C47: Julie Jones | D47: 251 | E47: 1167.21 | F47: 141866.01 | H47: =IF(ISBLANK(F47), "",(F47+G47)) -> 141866.01 | I47: =IF(ISBLANK(F47), "", E47/H47) -> 0.0082275522
A48: 1062 | B48: MARK HAGEMEISTER HOUSEHOLD | C48: Beth Arnold | D48: 162 | E48: 2632.72 | F48: 136797.11 | G48: 202.89 | H48: =IF(ISBLANK(F48), "",(F48+G48)) -> 137000 | I48: =IF(ISBLANK(F48), "", E48/H48) -> 0.019216934
A49: 1063 | B49: TRAVELING TRAINER LLC HOUSEHOLD | C49: Beth Arnold | D49: 162 | E49: -49.42 | F49: 119187.9 | H49: =IF(ISBLANK(F49), "",(F49+G49)) -> 119187.9 | I49: =IF(ISBLANK(F49), "", E49/H49) -> -0.00041463941
A50: 1065 | B50: AB INC HOUSEHOLD | C50: Beth Arnold | D50: 162 | E50: 58265.46 | H50: =IF(ISBLANK(F50), "",(F50+G50)) | I50: =IF(ISBLANK(F50), "", E50/H50)
A51: 1066 | B51: ADE INCORPORATED HOUSEHOLD | C51: Jennifer Sherby | D51: 151 | E51: 102975.41 | H51: =IF(ISBLANK(F51), "",(F51+G51)) | I51: =IF(ISBLANK(F51), "", E51/H51)
A52: 1067 | B52: ACCENT ON ART HOUSEHOLD | C52: Adrienne Flintoft | D52: 271 | E52: 20790.17 | H52: =IF(ISBLANK(F52), "",(F52+G52)) | I52: =IF(ISBLANK(F52), "", E52/H52)
A53: 1068 | B53: ADDISON TOWNSHIP LIBRARY HOUSEHOLD | C53: Beth Arnold | D53: 162 | E53: 117597.7 | H53: =IF(ISBLANK(F53), "",(F53+G53)) | I53: =IF(ISBLANK(F53), "", E53/H53)
A54: 1069 | B54: AMERICAN LEGION HOUSEHOLD | C54: Julie Jones | D54: 251 | E54: 279866.38 | F54: 0 | G54: 2500 | H54: =IF(ISBLANK(F54), "",(F54+G54)) -> 2500 | I54: =IF(ISBLANK(F54), "", E54/H54) -> 111.94655
A55: 107 | B55: Jidas Custom Homes Inc Household | C55: Julie Jones | D55: 251 | E55: 348313.83 | F55: 0 | G55: 1000 | H55: =IF(ISBLANK(F55), "",(F55+G55)) -> 1000 | I55: =IF(ISBLANK(F55), "", E55/H55) -> 348.31383
A56: 1070 | B56: ABSOLUTE GREEN CORPORATION HOUSEHOLD | C56: Jennifer Sherby | D56: 151 | E56: 25548.93 | F56: 58402.04 | G56: 191597.96 | H56: =IF(ISBLANK(F56), "",(F56+G56)) -> 250000 | I56: =IF(ISBLANK(F56), "", E56/H56) -> 0.10219572
A57: 1071 | B57: ADVANCE SCRAPING CO HOUSEHOLD | C57: Julie Jones | D57: 251 | E57: 10502.24 | H57: =IF(ISBLANK(F57), "",(F57+G57)) | I57: =IF(ISBLANK(F57), "", E57/H57)
A58: 1072 | B58: DENNIS ASHTON HOUSEHOLD | C58: Taylor Spicer | D58: 467 | E58: 116218.09 | H58: =IF(ISBLANK(F58), "",(F58+G58)) | I58: =IF(ISBLANK(F58), "", E58/H58)
A59: 1073 | B59: ADDISON PLUMBING CO HOUSEHOLD | C59: Beth Arnold | D59: 162 | E59: 326609.84 | H59: =IF(ISBLANK(F59), "",(F59+G59)) | I59: =IF(ISBLANK(F59), "", E59/H59)
A60: 1074 | B60: ALL SPORTS BRANDON BOOSTERS HOUSEHOLD | C60: Taylor Spicer | D60: 467 | E60: 15879.7 | H60: =IF(ISBLANK(F60), "",(F60+G60)) | I60: =IF(ISBLANK(F60), "", E60/H60)
A61: 1075 | B61: ALMONT AREA SENIOR CITIZENS HOUSEHOLD | C61: Beth Arnold | D61: 162 | E61: 12260.82 | H61: =IF(ISBLANK(F61), "",(F61+G61)) | I61: =IF(ISBLANK(F61), "", E61/H61)
A62: 1076 | B62: ADDISON TWP FIREFIGHTERS ASSOC HOUSEHOLD | C62: Julie Jones | D62: 251 | E62: 42897.24 | H62: =IF(ISBLANK(F62), "",(F62+G62)) | I62: =IF(ISBLANK(F62), "", E62/H62)
A63: 1077 | B63: ALMONT DRYDEN LODGE NO 51 HOUSEHOLD | C63: Beth Arnold | D63: 162 | E63: 17714.96 | H63: =IF(ISBLANK(F63), "",(F63+G63)) | I63: =IF(ISBLANK(F63), "", E63/H63)
A64: 1078 | B64: ADDISON MEADOWS ASSOCIATION HOUSEHOLD | C64: Beth Arnold | D64: 162 | E64: 7651.16 | H64: =IF(ISBLANK(F64), "",(F64+G64)) | I64: =IF(ISBLANK(F64), "", E64/H64)
A65: 1079 | B65: AARON ENGLER CERTIFIED FARRIER INC HOUSEHOLD | C65: Beth Arnold | D65: 162 | E65: 162371.88 | H65: =IF(ISBLANK(F65), "",(F65+G65)) | I65: =IF(ISBLANK(F65), "", E65/H65)
A66: 108 | B66: John Hicks Household | C66: Beth Arnold | D66: 162 | E66: 594.03 | H66: =IF(ISBLANK(F66), "",(F66+G66)) | I66: =IF(ISBLANK(F66), "", E66/H66)
A67: 1080 | B67: AMELL INC HOUSEHOLD | C67: Beth Arnold | D67: 162 | E67: 168879.53 | H67: =IF(ISBLANK(F67), "",(F67+G67)) | I67: =IF(ISBLANK(F67), "", E67/H67)
A68: 1081 | B68: GARY AHLBERG HOUSEHOLD | C68: Beth Arnold | D68: 162 | E68: 30638.37 | H68: =IF(ISBLANK(F68), "",(F68+G68)) | I68: =IF(ISBLANK(F68), "", E68/H68)
... A72: 1085 | B72: GRAZING LIFE LLC HOUSEHOLD | C72: Beth Arnold | D72: 162 | E72: 309766.27 | H72: =IF(ISBLANK(F72), "",(F72+G72)) | I72: =IF(ISBLANK(F72), "", E72/H72)
A73: 1086 | B73: MA MANAGEMENT GROUP HOUSEHOLD | C73: Claire Marie Spencer | D73: 478 | E73: 4051.15 | F73: 337979.48 | H73: =IF(ISBLANK(F73), "",(F73+G73)) -> 337979.48 | I73: =IF(ISBLANK(F73), "", E73/H73) -> 0.011986379
A74: 1087 | B74: VALOR SALON HOUSEHOLD | C74: Julie Jones | D74: 251 | E74: 4371.33 | F74: 531420.26 | G74: 96079.74 | H74: =IF(ISBLANK(F74), "",(F74+G74)) -> 627500 | I74: =IF(ISBLANK(F74), "", E74/H74) -> 0.0069662629
A75: 1088 | B75: HAINES DRAINS HOUSEHOLD | C75: Jennifer Sherby | D75: 151 | E75: 12590.9 | F75: 256729.7 | G75: 583.91 | H75: =IF(ISBLANK(F75), "",(F75+G75)) -> 257313.61 | I75: =IF(ISBLANK(F75), "", E75/H75) -> 0.048932118
A76: 1089 | B76: AMANDA GRAIN COMPANY HOUSEHOLD | C76: Beth Arnold | D76: 162 | E76: 146273.39 | H76: =IF(ISBLANK(F76), "",(F76+G76)) | I76: =IF(ISBLANK(F76), "", E76/H76)
A77: 109 | B77: Karen Mersino Household | C77: Brad Kirkland | D77: 618 | E77: 1619572.3 | F77: 206761 | G77: 294239 | H77: 794239 | I77: =IF(ISBLANK(F77), "", E77/H77) -> 2.0391499
A78: 1090 | B78: AQUA HEATING AND COOLING LLC HOUSEHOLD | C78: Julie Jones | D78: 251 | E78: 890792.58 | H78: =IF(ISBLANK(F78), "",(F78+G78)) | I78: =IF(ISBLANK(F78), "", E78/H78)
A79: 1091 | B79: A & D PRODUCTS LLC HOUSEHOLD | C79: Beth Arnold | D79: 162 | E79: 25879.41 | H79: =IF(ISBLANK(F79), "",(F79+G79)) | I79: =IF(ISBLANK(F79), "", E79/H79)
A80: 1092 | B80: A & G INVESTMENT PROPERTIES LTD HOUSEHOLD | C80: Taylor Spicer | D80: 467 | E80: 43795.42 | H80: =IF(ISBLANK(F80), "",(F80+G80)) | I80: =IF(ISBLANK(F80), "", E80/H80)
A81: 1093 | B81: DAVID BLOCKI HOUSEHOLD | C81: Beth Arnold | D81: 162 | E81: 72746.09 | H81: =IF(ISBLANK(F81), "",(F81+G81)) | I81: =IF(ISBLANK(F81), "", E81/H81)
A82: 1095 | B82: ALLEN DRESSAGE INC HOUSEHOLD | C82: Julie Jones | D82: 251 | E82: 76046.87 | H82: =IF(ISBLANK(F82), "",(F82+G82)) | I82: =IF(ISBLANK(F82), "", E82/H82)
A83: 1096 | B83: AURSAM PROPERTY SERVICES LLC HOUSEHOLD | C83: Julie Jones | D83: 251 | E83: 40750.84 | H83: =IF(ISBLANK(F83), "",(F83+G83)) | I83: =IF(ISBLANK(F83), "", E83/H83)
A84: 1098 | B84: ALIFETIME OF EVERYTHING LLC HOUSEHOLD | C84: Beth Arnold | D84: 162 | E84: 601.81 | H84: =IF(ISBLANK(F84), "",(F84+G84)) | I84: =IF(ISBLANK(F84), "", E84/H84)
A85: 11 | B85: NCG CINEMAS HOUSEHOLD | C85: Brad Kirkland | D85: 618 | E85: 593563.88 | F85: 8215408.8 | G85: 0 | H85: =IF(ISBLANK(F85), "",(F85+G85)) -> 8215408.8 | I85: =IF(ISBLANK(F85), "", E85/H85) -> 0.072250072
A86: 110 | B86: KC'S DAIRY TWIST HOUSEHOLD | C86: Jack Korth | D86: 653 | E86: 1201.58 | F86: 12377.6 | H86: =IF(ISBLANK(F86), "",(F86+G86)) -> 12377.6 | I86: =IF(ISBLANK(F86), "", E86/H86) -> 0.097076978
A87: 1100 | B87: ALPHABET CARPENTRY INC HOUSEHOLD | C87: Beth Arnold | D87: 162 | E87: 25841.35 | H87: =IF(ISBLANK(F87), "",(F87+G87)) | I87: =IF(ISBLANK(F87), "", E87/H87)
A88: 1101 | B88: PAMELA ALEXANDER HOUSEHOLD | C88: Nicole Curtiss | D88: 475 | E88: 25789.07 | H88: =IF(ISBLANK(F88), "",(F88+G88)) | I88: =IF(ISBLANK(F88), "", E88/H88)
A89: 1102 | B89: ATLEE MILLER FARRIER SERVICE LLC HOUSEHOLD | C89: Beth Arnold | D89: 162 | E89: 22099.62 | H89: =IF(ISBLANK(F89), "",(F89+G89)) | I89: =IF(ISBLANK(F89), "", E89/H89)
A90: 1103 | B90: AMERICAN CUTTING LLC HOUSEHOLD | C90: Beth Arnold | D90: 162 | E90: 28095.36 | H90: =IF(ISBLANK(F90), "",(F90+G90)) | I90: =IF(ISBLANK(F90), "", E90/H90)
A91: 1107 | B91: ACORN INDUSTRIES HOUSEHOLD | C91: Nicole Curtiss | D91: 475 | E91: 3174.7 | H91: =IF(ISBLANK(F91), "",(F91+G91)) | I91: =IF(ISBLANK(F91), "", E91/H91)
A92: 1108 | B92: WAYNE SLUITER HOUSEHOLD | C92: Nicole Curtiss | D92: 475 | E92: 28161.46 | H92: =IF(ISBLANK(F92), "",(F92+G92)) | I92: =IF(ISBLANK(F92), "", E92/H92)
A93: 1109 | B93: ADVANCED REMODELING & CONSTRUCTION LLC HOUSEHOLD | C93: Beth Arnold | D93: 162 | E93: 4999.6 | H93: =IF(ISBLANK(F93), "",(F93+G93)) | I93: =IF(ISBLANK(F93), "", E93/H93)
A94: 111 | B94: KENNETH LATSHAW HOUSEHOLD | C94: Adrienne Flintoft | D94: 271 | E94: 2459097.8 | F94: 14282.26 | G94: 35717.74 | H94: =IF(ISBLANK(F94), "",(F94+G94)) -> 50000 | I94: =IF(ISBLANK(F94), "", E94/H94) -> 49.181956
A95: 1110 | B95: NJ GALLAGHER CONTRACTOR LLC HOUSEHOLD | C95: Marlon Attiq | D95: 459 | E95: 108803.68 | H95: =IF(ISBLANK(F95), "",(F95+G95)) | I95: =IF(ISBLANK(F95), "", E95/H95)
A96: 1111 | B96: ROSATI MASON CONTRACTORS LLC HOUSEHOLD | C96: Jennifer Sherby | D96: 151 | E96: 1006717.7 | H96: =IF(ISBLANK(F96), "",(F96+G96)) | I96: =IF(ISBLANK(F96), "", E96/H96)
A97: 1112 | B97: DENNIS INGLES & SONS EXCAVATING LLC HOUSEHOLD | C97: Taylor Spicer | D97: 467 | E97: 150760.57 | H97: =IF(ISBLANK(F97), "",(F97+G97)) | I97: =IF(ISBLANK(F97), "", E97/H97)
A98: 1113 | B98: JON M GASKELL HOUSEHOLD | C98: Jennifer Sherby | D98: 151 | E98: 33166.33 | H98: =IF(ISBLANK(F98), "",(F98+G98)) | I98: =IF(ISBLANK(F98), "", E98/H98)
A99: 1114 | B99: GOODLOE BROTHERS LLC HOUSEHOLD | C99: Julie Jones | D99: 251 | E99: 5763.51 | H99: =IF(ISBLANK(F99), "",(F99+G99)) | I99: =IF(ISBLANK(F99), "", E99/H99)
A100: 1117 | B100: GLORIFIED INVESTMENT GROUP LLC HOUSEHOLD | C100: Jennifer Sherby | D100: 151 | E100: 2111.62 | H100: =IF(ISBLANK(F100), "",(F100+G100)) | I100: =IF(ISBLANK(F100), "", E100/H100)
A101: 1118 | B101: GOOD HANGS LLC HOUSEHOLD | C101: Julie Jones | D101: 251 | E101: 27786.71 | H101: =IF(ISBLANK(F101), "",(F101+G101)) | I101: =IF(ISBLANK(F101), "", E101/H101)
A102: 1119 | B102: GIRLS SCOUTS OF SOUTH EASTERN MI 78024 HOUSEHOLD | C102: Taylor Spicer | D102: 467 | E102: 5632.23 | H102: =IF(ISBLANK(F102), "",(F102+G102)) | I102: =IF(ISBLANK(F102), "", E102/H102)
A103: 1121 | B103: GREAT LAKES HEARING CARE LLC HOUSEHOLD | C103: Marlon Attiq | D103: 459 | E103: 216509.98 | H103: =IF(ISBLANK(F103), "",(F103+G103)) | I103: =IF(ISBLANK(F103), "", E103/H103)
...

Sheet Year end 2024
A1: Household ID | B1: Household Name | C1: Officer Code | D1: Officer Name | E1: Current Balance - Deposit | F1: Current Balance - Loan | G1: Available Balance | H1: Total Lending | I1: Ratio
A2: 1 | B2: MODERN BOOKKEEPING HOUSEHOLD | C2: Mark Morrison | D2: 615 | E2: 37995705 | F2: 785270.23 | G2: 1100000 | H2: =IF(ISBLANK(F2), "",(F2+G2)) -> 1885270.2 | I2: =IF(ISBLANK(F2), "", E2/H2) -> 20.153983
A3: 10 | B3: MARK CHERRY HOUSEHOLD | C3: Brad Kirkland | D3: 618 | E3: 23095.28 | F3: 577059.56 | G3: 161831.81 | H3: =IF(ISBLANK(F3), "",(F3+G3)) -> 738891.37 | I3: =IF(ISBLANK(F3), "", E3/H3) -> 0.031256665
A4: 100 | B4: Glenn A Bianchini Household | C4: Julie Jones | D4: 251 | E4: 28115.12 | H4: =IF(ISBLANK(F4), "",(F4+G4)) | I4: =IF(ISBLANK(F4), "", E4/H4)
A5: 1000 | B5: FUEL CELL ESA WCSU LLC HOUSEHOLD | C5: Mark Matheson | D5: 675 | E5: 0 | H5: =IF(ISBLANK(F5), "",(F5+G5)) | I5: =IF(ISBLANK(F5), "", E5/H5)
A6: 1001 | B6: CENTRACORE LLC HOUSEHOLD | C6: Julie Jones | D6: 251 | E6: 15614.22 | H6: =IF(ISBLANK(F6), "",(F6+G6)) | I6: =IF(ISBLANK(F6), "", E6/H6)
A7: 1002 | B7: CONSTABLE REAL ESTATE LLC HOUSEHOLD | C7: Marlon Attiq | D7: 459 | E7: 32971.55 | H7: =IF(ISBLANK(F7), "",(F7+G7)) | I7: =IF(ISBLANK(F7), "", E7/H7)
A8: 1003 | B8: ELISECO INC & NOVID LLC HOUSEHOLD | C8: Cary Listerman | D8: 130 | E8: 1295702 | F8: 0 | G8: 500000 | H8: =IF(ISBLANK(F8), "",(F8+G8)) -> 500000 | I8: =IF(ISBLANK(F8), "", E8/H8) -> 2.5914041
A9: 1004 | B9: SABRENY LP HOUSEHOLD | C9: Jose Morales | D9: 631 | E9: 5208.73 | H9: =IF(ISBLANK(F9), "",(F9+G9)) | I9: =IF(ISBLANK(F9), "", E9/H9)
A10: 1005 | B10: RONALD L NEWTON HOUSEHOLD | C10: FEM-Sam Bazido | D10: 436 | E10: 3710.58 | H10: =IF(ISBLANK(F10), "",(F10+G10)) | I10: =IF(ISBLANK(F10), "", E10/H10)
A11: 1006 | B11: CENTROIS LLC HOUSEHOLD | C11: Marlon Attiq | D11: 459 | E11: 594.72 | H11: =IF(ISBLANK(F11), "",(F11+G11)) | I11: =IF(ISBLANK(F11), "", E11/H11)
A12: 1007 | B12: KING CARPENTRY LLC HOUSEHOLD | C12: Julie Jones | D12: 251 | E12: 233698.99 | H12: =IF(ISBLANK(F12), "",(F12+G12)) | I12: =IF(ISBLANK(F12), "", E12/H12)
A13: 1008 | B13: INTERVENTIONAL PAIN CENTER PLLC HOUSEHOLD | C13: Marlon Attiq | D13: 459 | E13: 6031.65 | H13: =IF(ISBLANK(F13), "",(F13+G13)) | I13: =IF(ISBLANK(F13), "", E13/H13)
A14: 1009 | B14: INSPIRED CONCEPTS LLC HOUSEHOLD | C14: FEM-Sam Bazido | D14: 436 | E14: 57460.44 | H14: =IF(ISBLANK(F14), "",(F14+G14)) | I14: =IF(ISBLANK(F14), "", E14/H14)
A15: 101 | B15: Goodrich United Methodist Church Household | C15: Steve Tondreau | D15: 139 | E15: 142127 | F15: 12298.53 | H15: =IF(ISBLANK(F15), "",(F15+G15)) -> 12298.53 | I15: =IF(ISBLANK(F15), "", E15/H15) -> 11.556422
A16: 1010 | B16: THE GLAESER DAWES CORPORATION HOUSEHOLD | C16: Marlon Attiq | D16: 459 | E16: 2760.78 | H16: =IF(ISBLANK(F16), "",(F16+G16)) | I16: =IF(ISBLANK(F16), "", E16/H16)
A17: 1011 | B17: MAKOMI INC HOUSEHOLD | C17: Julie Jones | D17: 251 | E17: 847.49 | H17: =IF(ISBLANK(F17), "",(F17+G17)) | I17: =IF(ISBLANK(F17), "", E17/H17)
A18: 1012 | B18: TIMOTHY P ISRAEL HOUSEHOLD | C18: Beth Arnold | D18: 162 | E18: 337.61 | F18: 493672.27 | G18: 0 | H18: =IF(ISBLANK(F18), "",(F18+G18)) -> 493672.27 | I18: =IF(ISBLANK(F18), "", E18/H18) -> 0.00068387475
A19: 1013 | B19: JEREMY B STURZA HOUSEHOLD | C19: Julie Jones | D19: 251 | E19: 4004.73 | H19: =IF(ISBLANK(F19), "",(F19+G19)) | I19: =IF(ISBLANK(F19), "", E19/H19)
A20: 1014 | B20: DAVID M ROSE HOUSEHOLD | C20: Adrienne Flintoft | D20: 271 | E20: 25899.68 | F20: 288722.31 | G20: 80000 | H20: =IF(ISBLANK(F20), "",(F20+G20)) -> 368722.31 | I20: =IF(ISBLANK(F20), "", E20/H20) -> 0.070241695
A21: 1015 | B21: MARK GESUALE HOUSEHOLD | C21: FEM-Sam Bazido | D21: 436 | E21: 19355.47 | F21: 379220.48 | G21: 120779.52 | H21: =IF(ISBLANK(F21), "",(F21+G21)) -> 500000 | I21: =IF(ISBLANK(F21), "", E21/H21) -> 0.03871094
A22: 1016 | B22: SAMUEL D SWEET PLC HOUSEHOLD | C22: Julie Jones | D22: 251 | E22: 30283.69 | F22: 231707.81 | H22: =IF(ISBLANK(F22), "",(F22+G22)) -> 231707.81 | I22: =IF(ISBLANK(F22), "", E22/H22) -> 0.13069775
A23: 1017 | B23: RICHARD A BLASUTIG HOUSEHOLD | C23: Beth Arnold | D23: 162 | E23: 1413.21 | F23: 181928.67 | H23: =IF(ISBLANK(F23), "",(F23+G23)) -> 181928.67 | I23: =IF(ISBLANK(F23), "", E23/H23) -> 0.0077679345
A24: 1018 | B24: DIANNE C KMIOTEK HOUSEHOLD | C24: FEM-Alecia Campbell | D24: 115 | E24: 188654.98 | H24: =IF(ISBLANK(F24), "",(F24+G24)) | I24: =IF(ISBLANK(F24), "", E24/H24)
A25: 1019 | B25: TIDY MRO ENTERPRISES LLC HOUSEHOLD | C25: Vladislav Peck | D25: 460 | E25: 396.82 | H25: =IF(ISBLANK(F25), "",(F25+G25)) | I25: =IF(ISBLANK(F25), "", E25/H25)
A26: 1020 | B26: CYPRESS RIDGE CONSULTING GROUP LLC HOUSEHOLD | C26: Cary Listerman | D26: 130 | E26: 286.9 | H26: =IF(ISBLANK(F26), "",(F26+G26)) | I26: =IF(ISBLANK(F26), "", E26/H26)
A27: 1024 | B27: LEON D HIEBER JR HOUSEHOLD | C27: Vladislav Peck | D27: 460 | E27: 105804.73 | H27: =IF(ISBLANK(F27), "",(F27+G27)) | I27: =IF(ISBLANK(F27), "", E27/H27)
A28: 1028 | B28: EDWARD D ROOS HOUSEHOLD | C28: Cary Listerman | D28: 130 | E28: 649899.15 | H28: =IF(ISBLANK(F28), "",(F28+G28)) | I28: =IF(ISBLANK(F28), "", E28/H28)
A29: 1029 | B29: SAVARINO PROPERTIES HOUSEHOLD | C29: Vladislav Peck | D29: 460 | E29: 1783.84 | H29: =IF(ISBLANK(F29), "",(F29+G29)) | I29: =IF(ISBLANK(F29), "", E29/H29)
A30: 103 | B30: FRIENDS OF THE CLARKSTON INDEPENDENCE HOUSEHOLD | C30: Jennifer Sherby | D30: 151 | E30: 61127.35 | H30: =IF(ISBLANK(F30), "",(F30+G30)) | I30: =IF(ISBLANK(F30), "", E30/H30)
A31: 1030 | B31: STUDENT ADVOCACY CENTER OF MICHIGAN INC HOUSEHOLD | C31: Cary Listerman | D31: 130 | E31: 269810.04 | H31: =IF(ISBLANK(F31), "",(F31+G31)) | I31: =IF(ISBLANK(F31), "", E31/H31)
A32: 1032 | B32: MICHELE SHAUGHNESSY HOUSEHOLD | C32: Cary Listerman | D32: 130 | E32: 295000 | H32: =IF(ISBLANK(F32), "",(F32+G32)) | I32: =IF(ISBLANK(F32), "", E32/H32)
A33: 1033 | B33: CANCER SUPPORT COMMUNITY HOUSEHOLD | C33: Vladislav Peck | D33: 460 | E33: 53993.86 | H33: =IF(ISBLANK(F33), "",(F33+G33)) | I33: =IF(ISBLANK(F33), "", E33/H33)
A34: 1034 | B34: EICHNER REALTY INC HOUSEHOLD | C34: Vladislav Peck | D34: 460 | E34: 19534.27 | H34: =IF(ISBLANK(F34), "",(F34+G34)) | I34: =IF(ISBLANK(F34), "", E34/H34)
A35: 1035 | B35: TMT MANAGEMENT INC HOUSEHOLD | C35: Marlon Attiq | D35: 459 | E35: 1373 | H35: =IF(ISBLANK(F35), "",(F35+G35)) | I35: =IF(ISBLANK(F35), "", E35/H35)
... A37: 1039 | B37: TEKSOFT SYSTEMS INC HOUSEHOLD | C37: Julie Jones | D37: 251 | E37: 316.73 | H37: =IF(ISBLANK(F37), "",(F37+G37)) | I37: =IF(ISBLANK(F37), "", E37/H37)
A38: 104 | B38: Independence Dental PC Household | C38: Marlon Attiq | D38: 459 | E38: 2451.12 | F38: 55340.32 | H38: =IF(ISBLANK(F38), "",(F38+G38)) -> 55340.32 | I38: =IF(ISBLANK(F38), "", E38/H38) -> 0.044291757
A39: 1040 | B39: SANDBEAR EXPRESS INC HOUSEHOLD | C39: Marlon Attiq | D39: 459 | E39: 18.03 | H39: =IF(ISBLANK(F39), "",(F39+G39)) | I39: =IF(ISBLANK(F39), "", E39/H39)
A40: 1041 | B40: JDI TRAVEL INC HOUSEHOLD | C40: FEM-Sam Bazido | D40: 436 | E40: 99.18 | H40: =IF(ISBLANK(F40), "",(F40+G40)) | I40: =IF(ISBLANK(F40), "", E40/H40)
A41: 1042 | B41: FINNEA GROUP LLC HOUSEHOLD | C41: Marlon Attiq | D41: 459 | E41: 3.85 | H41: =IF(ISBLANK(F41), "",(F41+G41)) | I41: =IF(ISBLANK(F41), "", E41/H41)
A42: 1043 | B42: CSV RESTAURANTS LLC HOUSEHOLD | C42: Julie Jones | D42: 251 | E42: 152.15 | H42: =IF(ISBLANK(F42), "",(F42+G42)) | I42: =IF(ISBLANK(F42), "", E42/H42)
A43: 1044 | B43: STRATEGIC SERVICES GROUP INC HOUSEHOLD | C43: FEM-Sam Bazido | D43: 436 | E43: 114653.79 | H43: =IF(ISBLANK(F43), "",(F43+G43)) | I43: =IF(ISBLANK(F43), "", E43/H43)
A44: 1045 | B44: PAINT CREEK MGMT LLC HOUSEHOLD | C44: Thomas Merrill | D44: 640 | E44: 1013422.1 | F44: 1776308.8 | H44: =IF(ISBLANK(F44), "",(F44+G44)) -> 1776308.8 | I44: =IF(ISBLANK(F44), "", E44/H44) -> 0.57052136
A45: 1046 | B45: MORTGAGE RESOURCE PLUS, INC HOUSEHOLD | C45: Thomas Merrill | D45: 640 | E45: 688240.2 | H45: =IF(ISBLANK(F45), "",(F45+G45)) | I45: =IF(ISBLANK(F45), "", E45/H45)
A46: 1047 | B46: LOVE INC OF NORTH OAKLAND COUNTY HOUSEHOLD | C46: Marlon Attiq | D46: 459 | E46: 42440.21 | H46: =IF(ISBLANK(F46), "",(F46+G46)) | I46: =IF(ISBLANK(F46), "", E46/H46)
A47: 1049 | B47: RWC GROUP LLC HOUSEHOLD | C47: Robert Harbers | D47: 752 | E47: 0 | H47: =IF(ISBLANK(F47), "",(F47+G47)) | I47: =IF(ISBLANK(F47), "", E47/H47)
A48: 105 | B48: CONSOLIDATED MEDICAL BILLING LLC HOUSEHOLD | C48: FEM-Danielle Mulka | D48: 180 | E48: 52404.93 | H48: =IF(ISBLANK(F48), "",(F48+G48)) | I48: =IF(ISBLANK(F48), "", E48/H48)
A49: 1050 | B49: MICHIGAN STRATEGIC FUND HOUSEHOLD | C49: Cary Listerman | D49: 130 | E49: 5841672 | H49: =IF(ISBLANK(F49), "",(F49+G49)) | I49: =IF(ISBLANK(F49), "", E49/H49)
A50: 1051 | B50: ORCHARD LABORATORIES CORP HOUSEHOLD | C50: FEM-Sam Bazido | D50: 436 | E50: 6665.7 | H50: =IF(ISBLANK(F50), "",(F50+G50)) | I50: =IF(ISBLANK(F50), "", E50/H50)
A51: 1052 | B51: MRA PROPERTIES LLC HOUSEHOLD | C51: FEM-Robert Marschall | D51: 617 | E51: 80774.76 | H51: =IF(ISBLANK(F51), "",(F51+G51)) | I51: =IF(ISBLANK(F51), "", E51/H51)
A52: 1053 | B52: DALE WELSH HOUSEHOLD | C52: Julie Jones | D52: 251 | E52: 301.2 | F52: 174539.42 | G52: 460.58 | H52: =IF(ISBLANK(F52), "",(F52+G52)) -> 175000 | I52: =IF(ISBLANK(F52), "", E52/H52) -> 0.0017211429
A53: 1054 | B53: GNS MANAGEMENT LLC HOUSEHOLD | C53: Jennifer Sherby | D53: 151 | E53: 2896.09 | F53: 0 | G53: 200000 | H53: =IF(ISBLANK(F53), "",(F53+G53)) -> 200000 | I53: =IF(ISBLANK(F53), "", E53/H53) -> 0.01448045
A54: 1055 | B54: KEVIN CORBIN HOUSEHOLD | C54: Lisa Goldsworthy | D54: 708 | E54: 137.09 | F54: 163970.63 | H54: =IF(ISBLANK(F54), "",(F54+G54)) -> 163970.63 | I54: =IF(ISBLANK(F54), "", E54/H54) -> 0.00083606436
A55: 1056 | B55: BURINGTON GOLF CAR RENTALS INC HOUSEHOLD | C55: Cary Listerman | D55: 130 | E55: 5489.73 | F55: 160009.58 | H55: =IF(ISBLANK(F55), "",(F55+G55)) -> 160009.58 | I55: =IF(ISBLANK(F55), "", E55/H55) -> 0.034308758
A56: 1057 | B56: GREGORY WECKLE HOUSEHOLD | C56: Julie Jones | D56: 251 | E56: 1202.65 | F56: 219615.56 | G56: 38350 | H56: =IF(ISBLANK(F56), "",(F56+G56)) -> 257965.56 | I56: =IF(ISBLANK(F56), "", E56/H56) -> 0.0046620564
A57: 1058 | B57: DBA GENO & SON PROPERTY MANAGEMENT HOUSEHOLD | C57: Julie Jones | D57: 251 | E57: 11497.58 | F57: 153590.92 | G57: 1300 | H57: =IF(ISBLANK(F57), "",(F57+G57)) -> 154890.92 | I57: =IF(ISBLANK(F57), "", E57/H57) -> 0.074230174
A58: 1059 | B58: MICROTECH SYSTEMS INC HOUSEHOLD | C58: Keagan Hinkley | D58: 452 | E58: 10241.23 | F58: 148907.7 | G58: 1092.3 | H58: =IF(ISBLANK(F58), "",(F58+G58)) -> 150000 | I58: =IF(ISBLANK(F58), "", E58/H58) -> 0.068274867
A59: 1061 | B59: EUGENE MEAGHER HOUSEHOLD | C59: Julie Jones | D59: 251 | E59: 927.03 | F59: 143748.31 | H59: =IF(ISBLANK(F59), "",(F59+G59)) -> 143748.31 | I59: =IF(ISBLANK(F59), "", E59/H59) -> 0.0064489802
A60: 1062 | B60: MARK HAGEMEISTER HOUSEHOLD | C60: Beth Arnold | D60: 162 | E60: 1225.82 | F60: 136757.03 | G60: 242.97 | H60: =IF(ISBLANK(F60), "",(F60+G60)) -> 137000 | I60: =IF(ISBLANK(F60), "", E60/H60) -> 0.0089475912
A61: 1063 | B61: TRAVELING TRAINER LLC HOUSEHOLD | C61: Beth Arnold | D61: 162 | E61: 589.79 | F61: 124728.18 | H61: =IF(ISBLANK(F61), "",(F61+G61)) -> 124728.18 | I61: =IF(ISBLANK(F61), "", E61/H61) -> 0.0047286026
A62: 1064 | B62: ADVANCED RESEARCH COMPANY HOUSEHOLD | C62: Keagan Hinkley | D62: 452 | E62: 548.4 | H62: =IF(ISBLANK(F62), "",(F62+G62)) | I62: =IF(ISBLANK(F62), "", E62/H62)
A63: 1065 | B63: AB INC HOUSEHOLD | C63: Beth Arnold | D63: 162 | E63: 58315.82 | H63: =IF(ISBLANK(F63), "",(F63+G63)) | I63: =IF(ISBLANK(F63), "", E63/H63)
A64: 1066 | B64: ADE INCORPORATED HOUSEHOLD | C64: Jennifer Sherby | D64: 151 | E64: 95798.22 | H64: =IF(ISBLANK(F64), "",(F64+G64)) | I64: =IF(ISBLANK(F64), "", E64/H64)
A65: 1067 | B65: ACCENT ON ART HOUSEHOLD | C65: Keagan Hinkley | D65: 452 | E65: 26567.07 | H65: =IF(ISBLANK(F65), "",(F65+G65)) | I65: =IF(ISBLANK(F65), "", E65/H65)
A66: 1068 | B66: ADDISON TOWNSHIP LIBRARY HOUSEHOLD | C66: Beth Arnold | D66: 162 | E66: 249235.13 | H66: =IF(ISBLANK(F66), "",(F66+G66)) | I66: =IF(ISBLANK(F66), "", E66/H66)
A67: 1069 | B67: AMERICAN LEGION HOUSEHOLD | C67: Julie Jones | D67: 251 | E67: 521186 | F67: 0 | G67: 2500 | H67: =IF(ISBLANK(F67), "",(F67+G67)) -> 2500 | I67: =IF(ISBLANK(F67), "", E67/H67) -> 208.4744
A68: 107 | B68: Jidas Custom Homes Inc Household | C68: Julie Jones | D68: 251 | E68: 478960.56 | F68: 0 | G68: 1000 | H68: =IF(ISBLANK(F68), "",(F68+G68)) -> 1000 | I68: =IF(ISBLANK(F68), "", E68/H68) -> 478.96056
A69: 1070 | B69: ABSOLUTE GREEN CORPORATION HOUSEHOLD | C69: Jennifer Sherby | D69: 151 | E69: 29909.33 | F69: 9230.41 | G69: 140769.59 | H69: =IF(ISBLANK(F69), "",(F69+G69)) -> 150000 | I69: =IF(ISBLANK(F69), "", E69/H69) -> 0.19939553
A70: 1071 | B70: ADVANCE SCRAPING CO HOUSEHOLD | C70: Julie Jones | D70: 251 | E70: 40480.49 | H70: =IF(ISBLANK(F70), "",(F70+G70)) | I70: =IF(ISBLANK(F70), "", E70/H70)
A71: 1072 | B71: DENNIS ASHTON HOUSEHOLD | C71: FEM-Danielle Mulka | D71: 180 | E71: 112014.28 | H71: =IF(ISBLANK(F71), "",(F71+G71)) | I71: =IF(ISBLANK(F71), "", E71/H71)
A72: 1073 | B72: ADDISON PLUMBING CO HOUSEHOLD | C72: Beth Arnold | D72: 162 | E72: 293074.25 | H72: =IF(ISBLANK(F72), "",(F72+G72)) | I72: =IF(ISBLANK(F72), "", E72/H72)
A73: 1074 | B73: ALL SPORTS BRANDON BOOSTERS HOUSEHOLD | C73: FEM-Danielle Mulka | D73: 180 | E73: 23863.67 | H73: =IF(ISBLANK(F73), "",(F73+G73)) | I73: =IF(ISBLANK(F73), "", E73/H73)
A74: 1075 | B74: ALMONT AREA SENIOR CITIZENS HOUSEHOLD | C74: Beth Arnold | D74: 162 | E74: 11894.45 | H74: =IF(ISBLANK(F74), "",(F74+G74)) | I74: =IF(ISBLANK(F74), "", E74/H74)
A75: 1076 | B75: ADDISON TWP FIREFIGHTERS ASSOC HOUSEHOLD | C75: Julie Jones | D75: 251 | E75: 27761.51 | H75: =IF(ISBLANK(F75), "",(F75+G75)) | I75: =IF(ISBLANK(F75), "", E75/H75)
A76: 1077 | B76: ALMONT DRYDEN LODGE NO 51 HOUSEHOLD | C76: Beth Arnold | D76: 162 | E76: 16396.37 | H76: =IF(ISBLANK(F76), "",(F76+G76)) | I76: =IF(ISBLANK(F76), "", E76/H76)
A77: 1078 | B77: ADDISON MEADOWS ASSOCIATION HOUSEHOLD | C77: Beth Arnold | D77: 162 | E77: 7111.16 | H77: =IF(ISBLANK(F77), "",(F77+G77)) | I77: =IF(ISBLANK(F77), "", E77/H77)
A78: 1079 | B78: AARON ENGLER CERTIFIED FARRIER INC HOUSEHOLD | C78: Beth Arnold | D78: 162 | E78: 680.16 | H78: =IF(ISBLANK(F78), "",(F78+G78)) | I78: =IF(ISBLANK(F78), "", E78/H78)
A79: 108 | B79: John Hicks Household | C79: Beth Arnold | D79: 162 | E79: 2685.9 | H79: =IF(ISBLANK(F79), "",(F79+G79)) | I79: =IF(ISBLANK(F79), "", E79/H79)
A80: 1080 | B80: AMELL INC HOUSEHOLD | C80: Beth Arnold | D80: 162 | E80: 213138.36 | H80: =IF(ISBLANK(F80), "",(F80+G80)) | I80: =IF(ISBLANK(F80), "", E80/H80)
A81: 1081 | B81: GARY AHLBERG HOUSEHOLD | C81: Beth Arnold | D81: 162 | E81: 16310.65 | H81: =IF(ISBLANK(F81), "",(F81+G81)) | I81: =IF(ISBLANK(F81), "", E81/H81)
... A85: 1085 | B85: GRAZING LIFE LLC HOUSEHOLD | C85: Beth Arnold | D85: 162 | E85: 176826.61 | H85: =IF(ISBLANK(F85), "",(F85+G85)) | I85: =IF(ISBLANK(F85), "", E85/H85)
A86: 1086 | B86: MA MANAGEMENT GROUP HOUSEHOLD | C86: FEM-Alex Litchfield | D86: 643 | E86: 5188.88 | F86: 347881.15 | H86: =IF(ISBLANK(F86), "",(F86+G86)) -> 347881.15 | I86: =IF(ISBLANK(F86), "", E86/H86) -> 0.014915669
A87: 1087 | B87: VALOR SALON HOUSEHOLD | C87: Julie Jones | D87: 251 | E87: 10928.17 | F87: 50000 | G87: 0 | H87: =IF(ISBLANK(F87), "",(F87+G87)) -> 50000 | I87: =IF(ISBLANK(F87), "", E87/H87) -> 0.2185634
A88: 1088 | B88: HAINES DRAINS HOUSEHOLD | C88: Jennifer Sherby | D88: 151 | E88: 7480.61 | F88: 275786.11 | G88: 583.91 | H88: =IF(ISBLANK(F88), "",(F88+G88)) -> 276370.02 | I88: =IF(ISBLANK(F88), "", E88/H88) -> 0.027067371
A89: 1089 | B89: AMANDA GRAIN COMPANY HOUSEHOLD | C89: Beth Arnold | D89: 162 | E89: 81033.87 | H89: =IF(ISBLANK(F89), "",(F89+G89)) | I89: =IF(ISBLANK(F89), "", E89/H89)
A90: 109 | B90: Karen Mersino Household | C90: FEM-Robert Marschall | D90: 617 | E90: 6821213.7 | F90: 730395.8 | G90: 1000 | H90: =IF(ISBLANK(F90), "",(F90+G90)) -> 731395.8 | I90: =IF(ISBLANK(F90), "", E90/H90) -> 9.3262959
A91: 1090 | B91: AQUA HEATING AND COOLING LLC HOUSEHOLD | C91: Julie Jones | D91: 251 | E91: 856217.23 | H91: =IF(ISBLANK(F91), "",(F91+G91)) | I91: =IF(ISBLANK(F91), "", E91/H91)
A92: 1091 | B92: A & D PRODUCTS LLC HOUSEHOLD | C92: Beth Arnold | D92: 162 | E92: 22545.46 | H92: =IF(ISBLANK(F92), "",(F92+G92)) | I92: =IF(ISBLANK(F92), "", E92/H92)
A93: 1092 | B93: A & G INVESTMENT PROPERTIES LTD HOUSEHOLD | C93: FEM-Danielle Mulka | D93: 180 | E93: 45158.95 | H93: =IF(ISBLANK(F93), "",(F93+G93)) | I93: =IF(ISBLANK(F93), "", E93/H93)
A94: 1093 | B94: DAVID BLOCKI HOUSEHOLD | C94: Beth Arnold | D94: 162 | E94: 38939.05 | H94: =IF(ISBLANK(F94), "",(F94+G94)) | I94: =IF(ISBLANK(F94), "", E94/H94)
A95: 1094 | B95: APEX ENGINEERED SYSTEMS LLC HOUSEHOLD | C95: Keagan Hinkley | D95: 452 | E95: 244.9 | H95: =IF(ISBLANK(F95), "",(F95+G95)) | I95: =IF(ISBLANK(F95), "", E95/H95)
A96: 1095 | B96: ALLEN DRESSAGE INC HOUSEHOLD | C96: Julie Jones | D96: 251 | E96: 87199.83 | H96: =IF(ISBLANK(F96), "",(F96+G96)) | I96: =IF(ISBLANK(F96), "", E96/H96)
A97: 1096 | B97: AURSAM PROPERTY SERVICES LLC HOUSEHOLD | C97: Julie Jones | D97: 251 | E97: 40722.81 | H97: =IF(ISBLANK(F97), "",(F97+G97)) | I97: =IF(ISBLANK(F97), "", E97/H97)
A98: 11 | B98: NCG CINEMAS HOUSEHOLD | C98: Brad Kirkland | D98: 618 | E98: 2821497.4 | F98: 7691757.6 | G98: 0 | H98: =IF(ISBLANK(F98), "",(F98+G98)) -> 7691757.6 | I98: =IF(ISBLANK(F98), "", E98/H98) -> 0.36682089
A99: 110 | B99: KC'S DAIRY TWIST HOUSEHOLD | C99: Beth Arnold | D99: 162 | E99: 483.18 | F99: 12709.1 | H99: =IF(ISBLANK(F99), "",(F99+G99)) -> 12709.1 | I99: =IF(ISBLANK(F99), "", E99/H99) -> 0.038018428
A100: 1100 | B100: ALPHABET CARPENTRY INC HOUSEHOLD | C100: Beth Arnold | D100: 162 | E100: 22030.49 | H100: =IF(ISBLANK(F100), "",(F100+G100)) | I100: =IF(ISBLANK(F100), "", E100/H100)
A101: 1101 | B101: PAMELA ALEXANDER HOUSEHOLD | C101: FEM-Alecia Campbell | D101: 115 | E101: 29848.95 | H101: =IF(ISBLANK(F101), "",(F101+G101)) | I101: =IF(ISBLANK(F101), "", E101/H101)
A102: 1102 | B102: ATLEE MILLER FARRIER SERVICE LLC HOUSEHOLD | C102: Beth Arnold | D102: 162 | E102: 15803.62 | H102: =IF(ISBLANK(F102), "",(F102+G102)) | I102: =IF(ISBLANK(F102), "", E102/H102)
A103: 1103 | B103: AMERICAN CUTTING LLC HOUSEHOLD | C103: Beth Arnold | D103: 162 | E103: 52996.93 | H103: =IF(ISBLANK(F103), "",(F103+G103)) | I103: =IF(ISBLANK(F103), "", E103/H103)
A104: 1104 | B104: AKPINAR CHILDRENS CLINIC PC HOUSEHOLD | C104: Julie Jones | D104: 251 | E104: 513.19 | H104: =IF(ISBLANK(F104), "",(F104+G104)) | I104: =IF(ISBLANK(F104), "", E104/H104)
...
